Workbook
Name Antal_instanser: 'DKK - Safespring-tjenester 2025'!#REF!
Name Antal_instanser: 'EUR - Safespring services 2025'!#REF!
Name Antal_instanser: 'NOK - Safespring tjenester 2025'!#REF!
Name Antal_instanser: 'SEK - Safesprings tjänster 2025'!#REF!
Name BAAS_large_EUR: Data!$F$27
Name BAAS_large_SEK: Data!$E$27
Name BAAS_large.fee_EUR: Data!$F$25
Name BAAS_large.fee_SEK: Data!$E$25
Name BAAS_on.demand_EUR: Data!$F$23
Name BAAS_on.demand_SEK: Data!$E$23
Name BAAS_small_EUR: Data!$F$26
Name BAAS_small_SEK: Data!$E$26
Name BAAS_small.fee_EUR: Data!$F$24
Name BAAS_small.fee_SEK: Data!$E$24
Name Disk__GB: 'DKK - Safespring-tjenester 2025'!#REF!
Name Disk__GB: 'EUR - Safespring services 2025'!#REF!
Name Disk__GB: 'NOK - Safespring tjenester 2025'!#REF!
Name Disk__GB: 'SEK - Safesprings tjänster 2025'!#REF!
Name EUR: Data!$K$4
Name IAAS_GPU_A2_EUR: Data!$F$9
Name IAAS_GPU_A2_SEK: Data!$E$9
Name IAAS_gpu_EUR: Data!$F$7
Name IAAS_GPU_H100_EUR: Data!$F$10
Name IAAS_GPU_H100_SEK: Data!$E$10
Name IAAS_gpu_SEK: Data!$E$7
Name IAAS_gpu_SUNET: Data!$G$7
Name IAAS_nvme_EUR: Data!$F$6
Name IAAS_nvme_SEK: Data!$E$6
Name IAAS_nvme_SUNET: Data!$G$6
Name IAAS_pcpu_EUR: Data!$F$8
Name IAAS_pcpu_SEK: Data!$E$8
Name IAAS_pcpu_SUNET: Data!$G$8
Name IAAS_ram_EUR: Data!$F$3
Name IAAS_ram_SEK: Data!$E$3
Name IAAS_ram_SUNET: Data!$G$3
Name IAAS_ram_sunet_b_m: Data!$G$9
Name IAAS_ssd_EUR: Data!$F$4
Name IAAS_ssd_SEK: Data!$E$4
Name IAAS_ssd_SUNET: Data!$G$11
Name IAAS_vcpu_EUR: Data!$F$5
Name IAAS_vcpu_SEK: Data!$E$5
Name IAAS_vcpu_SUNET: Data!$G$5
Name IAAS_vcpu_sunet_b_m: Data!$G$10
Name INSTANCE_p1.2xlarge.16d_EUR: Data!$F$14
Name INSTANCE_p1.2xlarge.16d_SEK: Data!$E$14
Name INSTANCE_p1.4xlarge.16d_EUR: Data!$F$15
Name INSTANCE_p1.4xlarge.16d_SEK: Data!$E$15
Name INSTANCE_p1.8xlarge.32d_EUR: Data!$F$16
Name INSTANCE_p1.8xlarge.32d_SEK: Data!$E$16
Name list_Antal_instanser: 'DKK - Safespring-tjenester 2025'!#REF!
Name list_Antal_instanser: 'EUR - Safespring services 2025'!#REF!
Name list_Antal_instanser: 'NOK - Safespring tjenester 2025'!#REF!
Name list_Antal_instanser: 'SEK - Safesprings tjänster 2025'!#REF!
Name list_Disk__GB: 'DKK - Safespring-tjenester 2025'!#REF!
Name list_Disk__GB: 'EUR - Safespring services 2025'!#REF!
Name list_Disk__GB: 'NOK - Safespring tjenester 2025'!#REF!
Name list_Disk__GB: 'SEK - Safesprings tjänster 2025'!#REF!
Name list_RAM__GB: 'DKK - Safespring-tjenester 2025'!#REF!
Name list_RAM__GB: 'EUR - Safespring services 2025'!#REF!
Name list_RAM__GB: 'NOK - Safespring tjenester 2025'!#REF!

Sheet EUR - Safespring services 2025
B5: Price calculator 2026-05-25
B8: Contact Safespring | D8: Currency
B9: Call us: +46 8-55 10 73 56
B10: hello@safespring.com
B15: Safespring Kubernetes Engine
B18: All prices are in EUR, excluding VAT.
B19: Instructions: Fill in the desired quantity in the colored fields.
B22: Control plane
B23: The first control plane is managed, but unmanaged control planes can be added afterwards.
B24: Product ID | G24: Hourly | H24: 30 days | I24: Amount | K24: Infrastructure
B25: Managed Control plane | G25: =H25/720 -> 0.63972222 | H25: 460.6 | K25: =ROUNDUP(I25*H25,2) -> 0
B26: Unmanaged Control plane | G26: =H26/720 -> 0 | H26: 0 | K26: =ROUNDUP(I26*H26,2) -> 0
B27: Total | I27: =SUM(I14:I26) -> 0 | K27: =SUM(K14:K26) -> 0
B30: Safespring Compute | IaaS
B33: Infrastructure as a service can run on an open source license or with a Windows license.
B34: All prices are in EUR, excluding VAT.
B35: Instructions: Fill in the desired quantity in the colored fields.
B38: Flavors with local NVMe storage
B39: Central block storage can be purchased for the instances. See "Central block storage" in the price list.
B40: Product ID | C40: vCPU | D40: RAM (GB) | E40: Local disk (GB) | F40: Hourly | G40: 30 days | I40: Amount | K40: Infrastructure
B41: FLAVOR-l2. c2 r4. 100 | C41: 2 | D41: 4 | E41: 100 | F41: =G41/720 -> 0.062666667 | G41: =C41*IAAS_vcpu_EUR+D41*IAAS_ram_EUR+E41*IAAS_nvme_EUR -> 45.12 | K41: =ROUNDUP(I41*G41,2) -> 0
B42: FLAVOR-l2. c2 r4. 500 | C42: 2 | D42: 4 | E42: 500 | F42: =G42/720 -> 0.11488889 | G42: =C42*IAAS_vcpu_EUR+D42*IAAS_ram_EUR+E42*IAAS_nvme_EUR -> 82.72 | K42: =ROUNDUP(I42*G42,2) -> 0
B43: FLAVOR-l2. c2 r4. 1000 | C43: 2 | D43: 4 | E43: 1000 | F43: =G43/720 -> 0.18016667 | G43: =C43*IAAS_vcpu_EUR+D43*IAAS_ram_EUR+E43*IAAS_nvme_EUR -> 129.72 | K43: =ROUNDUP(I43*G43,2) -> 0
B44: FLAVOR-l2. c4 r8. 100 | C44: 4 | D44: 8 | E44: 100 | F44: =G44/720 -> 0.11227778 | G44: =C44*IAAS_vcpu_EUR+D44*IAAS_ram_EUR+E44*IAAS_nvme_EUR -> 80.84 | K44: =ROUNDUP(I44*G44,2) -> 0
B45: FLAVOR-l2. c4 r8. 500 | C45: 4 | D45: 8 | E45: 500 | F45: =G45/720 -> 0.1645 | G45: =C45*IAAS_vcpu_EUR+D45*IAAS_ram_EUR+E45*IAAS_nvme_EUR -> 118.44 | K45: =ROUNDUP(I45*G45,2) -> 0
B46: FLAVOR-l2. c4 r8. 1000 | C46: 4 | D46: 8 | E46: 1000 | F46: =G46/720 -> 0.22977778 | G46: =C46*IAAS_vcpu_EUR+D46*IAAS_ram_EUR+E46*IAAS_nvme_EUR -> 165.44 | K46: =ROUNDUP(I46*G46,2) -> 0
B47: FLAVOR-l2. c8 r16. 100 | C47: 8 | D47: 16 | E47: 100 | F47: =G47/720 -> 0.2115 | G47: =C47*IAAS_vcpu_EUR+D47*IAAS_ram_EUR+E47*IAAS_nvme_EUR -> 152.28 | K47: =ROUNDUP(I47*G47,2) -> 0
B48: FLAVOR-l2. c8 r16. 500 | C48: 8 | D48: 16 | E48: 500 | F48: =G48/720 -> 0.26372222 | G48: =C48*IAAS_vcpu_EUR+D48*IAAS_ram_EUR+E48*IAAS_nvme_EUR -> 189.88 | K48: =ROUNDUP(I48*G48,2) -> 0
B49: FLAVOR-l2. c8 r16. 1000 | C49: 8 | D49: 16 | E49: 1000 | F49: =G49/720 -> 0.329 | G49: =C49*IAAS_vcpu_EUR+D49*IAAS_ram_EUR+E49*IAAS_nvme_EUR -> 236.88 | K49: =ROUNDUP(I49*G49,2) -> 0
B50: FLAVOR-l2. c16 r32. 100 | C50: 16 | D50: 32 | E50: 100 | F50: =G50/720 -> 0.40994444 | G50: =C50*IAAS_vcpu_EUR+D50*IAAS_ram_EUR+E50*IAAS_nvme_EUR -> 295.16 | K50: =ROUNDUP(I50*G50,2) -> 0
B51: FLAVOR-l2. c16 r32. 500 | C51: 16 | D51: 32 | E51: 500 | F51: =G51/720 -> 0.46216667 | G51: =C51*IAAS_vcpu_EUR+D51*IAAS_ram_EUR+E51*IAAS_nvme_EUR -> 332.76 | K51: =ROUNDUP(I51*G51,2) -> 0
B52: FLAVOR-l2. c16 r32. 1000 | C52: 16 | D52: 32 | E52: 1000 | F52: =G52/720 -> 0.52744444 | G52: =C52*IAAS_vcpu_EUR+D52*IAAS_ram_EUR+E52*IAAS_nvme_EUR -> 379.76 | K52: =ROUNDUP(I52*G52,2) -> 0
... B54: FLAVOR-l2. c32 r64. 1000 | C54: 32 | D54: 64 | E54: 1000 | F54: =G54/720 -> 0.92433333 | G54: =C54*IAAS_vcpu_EUR+D54*IAAS_ram_EUR+E54*IAAS_nvme_EUR -> 665.52 | K54: =ROUNDUP(I54*G54,2) -> 0
B55: Total | C55: {=SUM(C41:C54*I41:I54)} -> 0 | D55: {=SUM(D41:D54*I41:I54)&" GB"} -> 0 GB | E55: {=SUM(E41:E54*I41:I54)&" GB"} -> 0 GB | I55: =SUM(I41:I54) -> 0 | K55: =SUM(K41:K54) -> 0
B59: Flavors without local storage
B60: Central block storage can be purchased for the instances. See "Central block storage" in the price list.
B61: Product ID | C61: vCPU | D61: RAM (GB) | E61: Local disk (GB) | F61: Hourly | G61: 30 days | I61: Amount | K61: Infrastructure
B62: FLAVOR-b2. c1 r2 | C62: 1 | D62: 2 | E62: 0 | F62: =G62/720 -> 0.024805556 | G62: =C62*IAAS_vcpu_EUR+D62*IAAS_ram_EUR+E62*IAAS_ssd_EUR -> 17.86 | K62: =ROUNDUP(I62*G62,2) -> 0
B63: FLAVOR-b2. c1 r4 | C63: 1 | D63: 4 | E63: 0 | F63: =G63/720 -> 0.039166667 | G63: =C63*IAAS_vcpu_EUR+D63*IAAS_ram_EUR+E63*IAAS_ssd_EUR -> 28.2 | K63: =ROUNDUP(I63*G63,2) -> 0
B64: FLAVOR-b2. c2 r4 | C64: 2 | D64: 4 | E64: 0 | F64: =G64/720 -> 0.049611111 | G64: =C64*IAAS_vcpu_EUR+D64*IAAS_ram_EUR+E64*IAAS_ssd_EUR -> 35.72 | K64: =ROUNDUP(I64*G64,2) -> 0
B65: FLAVOR-b2. c2 r8 | C65: 2 | D65: 8 | E65: 0 | F65: =G65/720 -> 0.078333333 | G65: =C65*IAAS_vcpu_EUR+D65*IAAS_ram_EUR+E65*IAAS_ssd_EUR -> 56.4 | K65: =ROUNDUP(I65*G65,2) -> 0
B66: FLAVOR-b2 .c4 r8 | C66: 4 | D66: 8 | E66: 0 | F66: =G66/720 -> 0.099222222 | G66: =C66*IAAS_vcpu_EUR+D66*IAAS_ram_EUR+E66*IAAS_ssd_EUR -> 71.44 | K66: =ROUNDUP(I66*G66,2) -> 0
B67: FLAVOR-b2. c4 r16 | C67: 4 | D67: 16 | E67: 0 | F67: =G67/720 -> 0.15666667 | G67: =C67*IAAS_vcpu_EUR+D67*IAAS_ram_EUR+E67*IAAS_ssd_EUR -> 112.8 | K67: =ROUNDUP(I67*G67,2) -> 0
B68: FLAVOR-b2. c8 r16 | C68: 8 | D68: 16 | E68: 0 | F68: =G68/720 -> 0.19844444 | G68: =C68*IAAS_vcpu_EUR+D68*IAAS_ram_EUR+E68*IAAS_ssd_EUR -> 142.88 | K68: =ROUNDUP(I68*G68,2) -> 0
B69: FLAVOR-b2. c8 r32 | C69: 8 | D69: 32 | E69: 0 | F69: =G69/720 -> 0.31333333 | G69: =C69*IAAS_vcpu_EUR+D69*IAAS_ram_EUR+E69*IAAS_ssd_EUR -> 225.6 | K69: =ROUNDUP(I69*G69,2) -> 0
B70: FLAVOR-b2. c16 r32 | C70: 16 | D70: 32 | E70: 0 | F70: =G70/720 -> 0.39688889 | G70: =C70*IAAS_vcpu_EUR+D70*IAAS_ram_EUR+E70*IAAS_ssd_EUR -> 285.76 | K70: =ROUNDUP(I70*G70,2) -> 0
B71: FLAVOR-b2. c16 r64 | C71: 16 | D71: 64 | E71: 0 | F71: =G71/720 -> 0.62666667 | G71: =C71*IAAS_vcpu_EUR+D71*IAAS_ram_EUR+E71*IAAS_ssd_EUR -> 451.2 | K71: =ROUNDUP(I71*G71,2) -> 0
B72: Total | C72: {=SUM(C62:C71*I62:I71)} -> 0 | D72: {=SUM(D62:D71*I62:I71)} -> 0 | E72: N/A | I72: =SUM(I62:I71) -> 0 | K72: =SUM(K62:K71) -> 0
B76: Flavors with GPU
B77: Central block storage can be purchased for the instances. See "Central block storage" in the price list.
B78: Product ID | C78: vCPU | D78: RAM (GB) | E78: Local disk (GB) | F78: Nvidia | G78: Hourly | H78: 30 days | I78: Amount | K78: Infrastructure
B79: FLAVOR-l2.c4r16.125.gA2 | C79: 4 | D79: 16 | E79: 125 | F79: A2 | G79: =H79/720 -> 0.43670833 | H79: =C79*IAAS_vcpu_EUR+D79*IAAS_ram_EUR+E79*IAAS_nvme_EUR+IAAS_GPU_A2_EUR -> 314.43 | K79: =ROUNDUP(I79*H79,2) -> 0
B80: FLAVOR-l2.c8r32.250.gA2 | C80: 8 | D80: 32 | E80: 250 | F80: A2 | G80: =H80/720 -> 0.60969444 | H80: =C80*IAAS_vcpu_EUR+D80*IAAS_ram_EUR+E80*IAAS_nvme_EUR+IAAS_GPU_A2_EUR -> 438.98 | K80: =ROUNDUP(I80*H80,2) -> 0
B81: FLAVOR-b2.c4r8.gA2 | C81: 4 | D81: 8 | E81: 0 | F81: A2 | G81: =H81/720 -> 0.36294444 | H81: =C81*IAAS_vcpu_EUR+D81*IAAS_ram_EUR+E81*IAAS_nvme_EUR+IAAS_GPU_A2_EUR -> 261.32 | K81: =ROUNDUP(I81*H81,2) -> 0
B82: FLAVOR-b2.c8r16.gA2 | C82: 8 | D82: 16 | E82: 0 | F82: A2 | G82: =H82/720 -> 0.46216667 | H82: =C82*IAAS_vcpu_EUR+D82*IAAS_ram_EUR+E82*IAAS_nvme_EUR+IAAS_GPU_A2_EUR -> 332.76 | K82: =ROUNDUP(I82*H82,2) -> 0
B83: FLAVOR-b2.c32.r192.gH100 | C83: 32 | D83: 192 | E83: 0 | F83: H100 | G83: =H83/720 -> 3.1364667 | H83: =C83*IAAS_vcpu_EUR+D83*IAAS_ram_EUR+E83*IAAS_nvme_EUR+IAAS_GPU_H100_EUR -> 2258.256 | K83: =ROUNDUP(I83*H83,2) -> 0
B84: Total | C84: =SUMPRODUCT(C79:C83,I79:I83) -> 0 | D84: =SUMPRODUCT(D79:D83,I79:I83)&" GB" -> 0 GB | E84: =SUMPRODUCT(E79:E83,I79:I83)&" GB" -> 0 GB | I84: =SUM(I79:I83) -> 0 | K84: =SUM(K79:K83) -> 0
B88: Central block storage
B89: Central block storage provides three copies of the data distributed in a robust CEPH cluster.
B90: Product ID | C90: Description | F90: Hourly | G90: 30 days | I90: Amount (GB) | K90: Storage
B91: VOLUME-large | C91: HDD-backed 3-replica Ceph | F91: =G91/720 -> 0.00015666667 | G91: =VOLUME_large_EUR -> 0.1128 | K91: =ROUNDUP(I91*G91,2) -> 0
B92: VOLUME-fast | C92: SSD-backed 3-replica Ceph | F92: =G92/720 -> 0.00047 | G92: =VOLUME_fast_EUR -> 0.3384 | K92: =ROUNDUP(I92*G92,2) -> 0
B93: VOLUME-snapshot | C93: Snapshot of image | F93: =G93/720 -> 0.00015666667 | G93: =VOLUME_large_EUR -> 0.1128 | K93: =ROUNDUP(I93*G93,2) -> 0
B94: Total | I94: =SUM(I91:I93)&" GB" -> 0 GB | K94: =SUM(K91:K93) -> 0
B98: Safespring Storage | S3
B101: Contact us for discounts on larger storage quantities. Pricing model based on the number of stored TB per month.
B102: All prices are in EUR, excluding VAT.
B103: Instructions: Fill in the desired quantity in the colored fields.
B105: Product ID | G105: Per TB for 30 days | I105: Amount (TB) | K105: Storage
B106: S3-archive | C106: Designed for larger storage volumes over longer periods. | G106: =S3_archive.50_EUR -> 32.9 | K106: =I106*G106 -> 0
B107: S3-storage | C107: Designed for applications that actively use the S3 protocol. | G107: =S3_storage50_EUR -> 47 | K107: =I107*G107 -> 0
B108: Total | K108: =SUM(K106:K107) -> 0
B112: Safespring Backup | SP
B115: Cloud backup solution for on-prem or cloud servers based on Spectrum Protect (TSM).
B116: All prices are in EUR, excluding VAT.
B117: Instructions: Fill in the desired quantity in the colored fields.
B119: Product ID | E119: Fixed monthly price | G119: Per GB / 30 days | I119: Amount (GB) | J119: Deduplication 1 | K119: Backup
B120: BAAS-on.demand 2 | E120: N/A | G120: =BAAS_on.demand_EUR -> 0.2303 | J120: N/A | K120: =ROUNDUP(I120*G120,2) -> 0
B121: BAAS-small 3 | E121: =BAAS_small.fee_EUR -> 517 | G121: =BAAS_small_EUR -> 0.1645 | J121: 0.75 | K121: =IF(I121>0,$E$121+$G$121*MAX(0,I121*(1-$J$121)-1000),0) -> 0
B122: BAAS-large 4 | E122: =BAAS_large.fee_EUR -> 893 | G122: =BAAS_large_EUR -> 0.08648 | J122: 0.75 | K122: =IF(I122>0,$E$122+($G$122*(I122*(1-$J$122))),0) -> 0
B123: Total | I123: =SUM(I120:I122)&" GB" -> 0 GB | K123: =SUM(K120:K122) -> 0
B127: Network and software
B130: All prices are in EUR, excluding VAT.
B132: Network
B133: Safespring offers several network services.
B134: Product ID | C134: Type | E134: Description | J134: Billing per | K134: Monthly
B135: NET-publicv4 | C135: IPv4 | E135: Public | J135: IP-address | K135: =NET_publicv4_EUR -> 2.35
B136: NET-publicv6 | C136: IPv6 | E136: Public | J136: N/A | K136: =NET_publicv6_EUR -> 0
B137: NET-ingress | C137: Data transfer | J137: GB | K137: =NET_ingress_EUR -> 0
B138: NET-egress | C138: Data transfer | J138: GB | K138: =NET_egress_EUR -> 0
B139: NET-mgn.slb | C139: Managed SLB (ElasticIP) | E139: Load balancers that require their own instances | J139: Instance | K139: Request a quote
B140: NET-rdns | C140: Reverse DNS names | J140: N/A | K140: =NET_rdns_EUR -> 0
B141: NET-byoip | C141: Bring your own IP prefixes | J141: N/A | K141: 0
B145: Software and licenses
B146: Safespring offers several software and licenses.
B147: Product ID | E147: Description | J147: Billing per | K147: Monthly
B148: SW-win.ser.2022 | E148: Microsoft Windows Server | J148: vCPU | K148: =SW_win.ser.201X_EUR -> 16.45
B149: SW-ms.sql.ser | E149: Microsoft SQL Server Standard | J149: vCPU | K149: =SW_ms.sql.ser_EUR -> 115.526
B150: SW-ms.sql.ser.ent | E150: Microsoft SQL Server Enterprise | J150: vCPU | K150: =SW_ms.sql.ser.ent_EUR -> 448.004
B154: Partner services
...

Sheet SEK - Safesprings tjänster 2025
B5: Priskalkylator 2026-05-25
B8: Kontakta Safespring | D8: Valuta
B9: Telefon: 08-55 10 73 56
B10: hello@safespring.com
B15: Safespring Kubernetes Engine
B18: Alla priser är angivna i SEK, exklusive moms.
B19: Instruktioner: Fyll i önskad kvantitet i de färgade fälten.
B22: Kontrollplan
B23: Första kontrollplanet är managerat men sedan går det att addera omanagerade kontrollplan.
B24: Produkt ID | G24: Per timme | H24: Per 30 dagar | I24: Antal instanser | K24: Totalt
B25: Managed Control plane | G25: =H25/720 -> 6.8055556 | H25: 4900 | K25: =ROUNDUP(I25*H25,2) -> 0
B26: Unmanaged Control plane | G26: =H26/720 -> 0 | H26: 0 | K26: =ROUNDUP(I26*H26,2) -> 0
B27: Totalt | I27: =SUM(I14:I26)&" st" -> 0 st | K27: =SUM(K14:K26) -> 0
B30: Safespring Compute | IaaS
B33: Infrastruktur kan köras med en Open Source-licens eller med en Windows-licens
B34: Alla priser är angivna i SEK, exklusive moms.
B35: Instruktioner: Fyll i önskad kvantitet i de färgade fälten.
B38: Flavors med lokal NVMe-disk
B39: Central blocklagring kan köpas till instanserna. Se "Central blocklagring" i prislistan.
B40: Produkt ID | C40: vCPU | D40: RAM (GB) | E40: Lokal disk (GB) | G40: Per timme | H40: Per 30 dagar | I40: Antal instanser | K40: Infrastruktur
B41: FLAVOR-l2. c2 r4. 100 | C41: 2 | D41: 4 | E41: 100 | G41: =H41/720 -> 0.66666667 | H41: =C41*IAAS_vcpu_SEK+D41*IAAS_ram_SEK+E41*IAAS_nvme_SEK -> 480 | K41: =ROUNDUP(I41*H41,2) -> 0
B42: FLAVOR-l2. c2 r4. 500 | C42: 2 | D42: 4 | E42: 500 | G42: =H42/720 -> 1.2222222 | H42: =C42*IAAS_vcpu_SEK+D42*IAAS_ram_SEK+E42*IAAS_nvme_SEK -> 880 | K42: =ROUNDUP(I42*H42,2) -> 0
B43: FLAVOR-l2. c2 r4. 1000 | C43: 2 | D43: 4 | E43: 1000 | G43: =H43/720 -> 1.9166667 | H43: =C43*IAAS_vcpu_SEK+D43*IAAS_ram_SEK+E43*IAAS_nvme_SEK -> 1380 | K43: =ROUNDUP(I43*H43,2) -> 0
B44: FLAVOR-l2. c4 r8. 100 | C44: 4 | D44: 8 | E44: 100 | G44: =H44/720 -> 1.1944444 | H44: =C44*IAAS_vcpu_SEK+D44*IAAS_ram_SEK+E44*IAAS_nvme_SEK -> 860 | K44: =ROUNDUP(I44*H44,2) -> 0
B45: FLAVOR-l2. c4 r8. 500 | C45: 4 | D45: 8 | E45: 500 | G45: =H45/720 -> 1.75 | H45: =C45*IAAS_vcpu_SEK+D45*IAAS_ram_SEK+E45*IAAS_nvme_SEK -> 1260 | K45: =ROUNDUP(I45*H45,2) -> 0
B46: FLAVOR-l2. c4 r8. 1000 | C46: 4 | D46: 8 | E46: 1000 | G46: =H46/720 -> 2.4444444 | H46: =C46*IAAS_vcpu_SEK+D46*IAAS_ram_SEK+E46*IAAS_nvme_SEK -> 1760 | K46: =ROUNDUP(I46*H46,2) -> 0
B47: FLAVOR-l2. c8 r16. 100 | C47: 8 | D47: 16 | E47: 100 | G47: =H47/720 -> 2.25 | H47: =C47*IAAS_vcpu_SEK+D47*IAAS_ram_SEK+E47*IAAS_nvme_SEK -> 1620 | K47: =ROUNDUP(I47*H47,2) -> 0
B48: FLAVOR-l2. c8 r16. 500 | C48: 8 | D48: 16 | E48: 500 | G48: =H48/720 -> 2.8055556 | H48: =C48*IAAS_vcpu_SEK+D48*IAAS_ram_SEK+E48*IAAS_nvme_SEK -> 2020 | K48: =ROUNDUP(I48*H48,2) -> 0
B49: FLAVOR-l2. c8 r16. 1000 | C49: 8 | D49: 16 | E49: 1000 | G49: =H49/720 -> 3.5 | H49: =C49*IAAS_vcpu_SEK+D49*IAAS_ram_SEK+E49*IAAS_nvme_SEK -> 2520 | K49: =ROUNDUP(I49*H49,2) -> 0
B50: FLAVOR-l2. c16 r32. 100 | C50: 16 | D50: 32 | E50: 100 | G50: =H50/720 -> 4.3611111 | H50: =C50*IAAS_vcpu_SEK+D50*IAAS_ram_SEK+E50*IAAS_nvme_SEK -> 3140 | K50: =ROUNDUP(I50*H50,2) -> 0
B51: FLAVOR-l2. c16 r32. 500 | C51: 16 | D51: 32 | E51: 500 | G51: =H51/720 -> 4.9166667 | H51: =C51*IAAS_vcpu_SEK+D51*IAAS_ram_SEK+E51*IAAS_nvme_SEK -> 3540 | K51: =ROUNDUP(I51*H51,2) -> 0
B52: FLAVOR-l2. c16 r32. 1000 | C52: 16 | D52: 32 | E52: 1000 | G52: =H52/720 -> 5.6111111 | H52: =C52*IAAS_vcpu_SEK+D52*IAAS_ram_SEK+E52*IAAS_nvme_SEK -> 4040 | K52: =ROUNDUP(I52*H52,2) -> 0
... B54: FLAVOR-l2. c32 r64. 1000 | C54: 32 | D54: 64 | E54: 1000 | G54: =H54/720 -> 9.8333333 | H54: =C54*IAAS_vcpu_SEK+D54*IAAS_ram_SEK+E54*IAAS_nvme_SEK -> 7080 | K54: =ROUNDUP(I54*H54,2) -> 0
B55: Totalt | C55: {=SUM(C41:C54*I41:I54)&" st"} -> 0 st | D55: {=SUM(D41:D54*I41:I54)&" GB"} -> 0 GB | E55: {=SUM(E41:E54*I41:I54)&" GB"} -> 0 GB | I55: =SUM(I41:I54)&" st" -> 0 st | K55: =SUM(K41:K54) -> 0
B59: Flavors utan lokal disk
B60: Central blocklagring kan köpas till instanserna. Se "Central blocklagring" i prislistan.
B61: Produkt ID | C61: vCPU | D61: RAM (GB) | E61: Lokal disk (GB) | G61: Per timme | H61: Per 30 dagar | I61: Antal instanser | K61: Infrastruktur
B62: FLAVOR-b2. c1 r2 | C62: 1 | D62: 2 | E62: 0 | G62: =H62/720 -> 0.26388889 | H62: =C62*IAAS_vcpu_SEK+D62*IAAS_ram_SEK+E62*IAAS_ssd_SEK -> 190 | K62: =ROUNDUP(I62*H62,2) -> 0
B63: FLAVOR-b2. c1 r4 | C63: 1 | D63: 4 | E63: 0 | G63: =H63/720 -> 0.41666667 | H63: =C63*IAAS_vcpu_SEK+D63*IAAS_ram_SEK+E63*IAAS_ssd_SEK -> 300 | K63: =ROUNDUP(I63*H63,2) -> 0
B64: FLAVOR-b2. c2 r4 | C64: 2 | D64: 4 | E64: 0 | G64: =H64/720 -> 0.52777778 | H64: =C64*IAAS_vcpu_SEK+D64*IAAS_ram_SEK+E64*IAAS_ssd_SEK -> 380 | K64: =ROUNDUP(I64*H64,2) -> 0
B65: FLAVOR-b2. c2 r8 | C65: 2 | D65: 8 | E65: 0 | G65: =H65/720 -> 0.83333333 | H65: =C65*IAAS_vcpu_SEK+D65*IAAS_ram_SEK+E65*IAAS_ssd_SEK -> 600 | K65: =ROUNDUP(I65*H65,2) -> 0
B66: FLAVOR-b2 .c4 r8 | C66: 4 | D66: 8 | E66: 0 | G66: =H66/720 -> 1.0555556 | H66: =C66*IAAS_vcpu_SEK+D66*IAAS_ram_SEK+E66*IAAS_ssd_SEK -> 760 | K66: =ROUNDUP(I66*H66,2) -> 0
B67: FLAVOR-b2. c4 r16 | C67: 4 | D67: 16 | E67: 0 | G67: =H67/720 -> 1.6666667 | H67: =C67*IAAS_vcpu_SEK+D67*IAAS_ram_SEK+E67*IAAS_ssd_SEK -> 1200 | K67: =ROUNDUP(I67*H67,2) -> 0
B68: FLAVOR-b2. c8 r16 | C68: 8 | D68: 16 | E68: 0 | G68: =H68/720 -> 2.1111111 | H68: =C68*IAAS_vcpu_SEK+D68*IAAS_ram_SEK+E68*IAAS_ssd_SEK -> 1520 | K68: =ROUNDUP(I68*H68,2) -> 0
B69: FLAVOR-b2. c8 r32 | C69: 8 | D69: 32 | E69: 0 | G69: =H69/720 -> 3.3333333 | H69: =C69*IAAS_vcpu_SEK+D69*IAAS_ram_SEK+E69*IAAS_ssd_SEK -> 2400 | K69: =ROUNDUP(I69*H69,2) -> 0
B70: FLAVOR-b2. c16 r32 | C70: 16 | D70: 32 | E70: 0 | G70: =H70/720 -> 4.2222222 | H70: =C70*IAAS_vcpu_SEK+D70*IAAS_ram_SEK+E70*IAAS_ssd_SEK -> 3040 | K70: =ROUNDUP(I70*H70,2) -> 0
B71: FLAVOR-b2. c16 r64 | C71: 16 | D71: 64 | E71: 0 | G71: =H71/720 -> 6.6666667 | H71: =C71*IAAS_vcpu_SEK+D71*IAAS_ram_SEK+E71*IAAS_ssd_SEK -> 4800 | K71: =ROUNDUP(I71*H71,2) -> 0
B72: Totalt | C72: {=SUM(C62:C71*I62:I71)} -> 0 | D72: {=SUM(D62:D71*I62:I71)} -> 0 | I72: =SUM(I62:I71)&" st" -> 0 st | K72: =SUM(K62:K71) -> 0
B76: Flavors med GPU
B77: Central blocklagring kan köpas till instanserna. Se "Central blocklagring" i prislistan.
B78: Produkt ID | C78: vCPU | D78: RAM (GB) | E78: Lokal disk (GB) | F78: Nvidia | G78: Per timme | H78: Per 30 dagar | I78: Antal instanser | K78: Infrastruktur
B79: FLAVOR-l2.c4r16.125.gA2 | C79: 4 | D79: 16 | E79: 125 | F79: A2 | G79: =H79/720 -> 4.6458333 | H79: =C79*IAAS_vcpu_SEK+D79*IAAS_ram_SEK+E79*IAAS_nvme_SEK+1*IAAS_GPU_A2_SEK -> 3345 | K79: =ROUNDUP(I79*H79,2) -> 0
B80: FLAVOR-l2.c8r32.250.gA2 | C80: 8 | D80: 32 | E80: 250 | F80: A2 | G80: =H80/720 -> 6.4861111 | H80: =C80*IAAS_vcpu_SEK+D80*IAAS_ram_SEK+E80*IAAS_nvme_SEK+1*IAAS_GPU_A2_SEK -> 4670 | K80: =ROUNDUP(I80*H80,2) -> 0
B81: FLAVOR-b2.c4r8.gA2 | C81: 4 | D81: 8 | E81: 0 | F81: A2 | G81: =H81/720 -> 3.8611111 | H81: =C81*IAAS_vcpu_SEK+D81*IAAS_ram_SEK+E81*IAAS_nvme_SEK+1*IAAS_GPU_A2_SEK -> 2780 | K81: =ROUNDUP(I81*H81,2) -> 0
B82: FLAVOR-b2.c8r16.gA2 | C82: 8 | D82: 16 | E82: 0 | F82: A2 | G82: =H82/720 -> 4.9166667 | H82: =C82*IAAS_vcpu_SEK+D82*IAAS_ram_SEK+E82*IAAS_nvme_SEK+1*IAAS_GPU_A2_SEK -> 3540 | K82: =ROUNDUP(I82*H82,2) -> 0
B83: FLAVOR-b2.c32.r192.gH100 | C83: 32 | D83: 192 | E83: 0 | F83: H100 | G83: =H83/720 -> 33.366667 | H83: =C83*IAAS_vcpu_SEK+D83*IAAS_ram_SEK+E83*IAAS_nvme_SEK+1*IAAS_GPU_H100_SEK -> 24024 | K83: =ROUNDUP(I83*H83,2) -> 0
B84: Totalt | C84: {=SUM(C79:C83*I79:I83)&" st"} -> 0 st | D84: =SUMPRODUCT(D79:D83,I79:I83)&" GB" -> 0 GB | E84: =SUMPRODUCT(E79:E83,I79:I83)&" GB" -> 0 GB | I84: =SUM(I79:I83)&" st" -> 0 st | K84: =SUM(K79:K83) -> 0
H87: =H83-24024 -> 0
B88: Central blocklagring
B89: Central blocklagring ger tre kopior av datat utspritt i ett robust CEPH-kluster.
B90: Produkt ID | C90: Beskrivning | G90: Per timme | H90: Per 30 dagar | I90: Extra GB | K90: Lagring
B91: VOLUME-large | C91: HDD-backed 3-replica Ceph | G91: =H91/720 -> 0.0016666667 | H91: =VOLUME_large_SEK -> 1.2 | K91: =ROUNDUP(I91*H91,2) -> 0
B92: VOLUME-fast | C92: SSD-backed 3-replica Ceph | G92: =H92/720 -> 0.005 | H92: =VOLUME_fast_SEK -> 3.6 | K92: =ROUNDUP(I92*H92,2) -> 0
B93: VOLUME-snapshot | C93: Snapshot of image | G93: =H93/720 -> 0.0016666667 | H93: =VOLUME_large_SEK -> 1.2 | K93: =ROUNDUP(I93*H93,2) -> 0
B94: Totalt | I94: =SUM(I91:I93)&" GB" -> 0 GB | K94: =SUM(K91:K93) -> 0
B97: Safespring Storage | S3
B100: Kontakta oss för rabatter vid större lagringsmängder. Prismodell baserad på antal lagrade TB i månaden.
B101: Alla priser är angivna i SEK, exklusive moms.
B102: Instruktioner: Fyll i önskad kvantitet i de färgade fälten.
B104: Produkt ID | G104: Per TB i 30 dagar | I104: Antal TB | K104: Storage
B105: S3-archive | C105: Anpassad för större lagringsvolymer över längre tid. | G105: =S3_archive.50_SEK -> 350 | K105: =I105*G105 -> 0
B106: S3-storage | C106: Anpassad för applikationer som aktivt använder S3-protokollet. | G106: =S3_storage50_SEK -> 500 | K106: =I106*G106 -> 0
B107: Totalt | K107: =SUM(K105:K106) -> 0
B110: Safespring Backup | SP
B113: Backup-lösning i cloud för lokala servrar eller molnservrar baserad på Spectrum Protect (TSM).
B114: Alla priser angivna i SEK, exklusive moms.
B115: Instruktioner: Fyll i önskad kvantitet i de färgade fälten.
B117: Produkt ID | E117: Fast månadspris | G117: Per GB i 30 dagar | I117: Antal GB | J117: Deduplicering 1 | K117: Backup
B118: BAAS-on.demand 2 | E118: N/A | G118: =BAAS_on.demand_SEK -> 2.45 | J118: N/A | K118: =ROUNDUP(I118*G118,2) -> 0
B119: BAAS-small 3 | E119: 5500 | G119: =BAAS_small_SEK -> 1.75 | J119: 0.75 | K119: =IF(I119>0,$E$119+$G$119*MAX(0,I119*(1-$J$119)-1000),0) -> 0
B120: BAAS-large 4 | E120: 9500 | G120: =BAAS_large_SEK -> 0.92 | J120: 0.75 | K120: =IF(I120>0,$E$120+($G$120*(I120*(1-$J$120))),0) -> 0
B121: Totalt | I121: =SUM(I118:I120)&" GB" -> 0 GB | K121: =SUM(K118:K120) -> 0
B125: Nätverk och programvara
B128: Alla priser angivna i SEK, exklusive moms.
B130: Nätverk
B131: Safespring erbjuder flera nätverkstjänster.
B132: Produkt ID | C132: Typ | E132: Beskrivning | J132: Debitering per | K132: Per månad
B133: NET-publicv4 | C133: IPv4 | E133: Publik | J133: IP-adress | K133: =NET_publicv4_SEK -> 25
B134: NET-publicv6 | C134: IPv6 | E134: Publik | J134: N/A | K134: =NET_publicv6_SEK -> 0
B135: NET-ingress | C135: Datatrafik | J135: GB | K135: =NET_ingress_SEK -> 0
B136: NET-egress | C136: Datatrafik | J136: GB | K136: =NET_egress_SEK -> 0
B137: NET-mgn.slb | C137: Managed SLB (ElasticIP) | E137: Lastbalanserare som kräver egna instanser | J137: Instans | K137: Begär offert
B138: NET-rdns | C138: Reverse DNS names | J138: N/A | K138: =NET_rdns_SEK -> 0
B139: NET-byoip | C139: Bring your own IP prefixes | J139: N/A | K139: 0
B143: Programvara och licenser
B144: Safespring erbjuder flera programvaror och licenser.
B145: Produkt ID | E145: Beskrivning | J145: Debitering per | K145: Per månad
B146: SW-win.ser.2022 | E146: Microsoft Windows Server | J146: vCPU | K146: =SW_win.ser.201X_SEK -> 175
B147: SW-ms.sql.ser | E147: Microsoft SQL Server Standard | J147: vCPU | K147: =SW_ms.sql.ser_SEK -> 1229
B148: SW-ms.sql.ser.ent | E148: Microsoft SQL Server Enterprise | J148: vCPU | K148: =SW_ms.sql.ser.ent_SEK -> 4766
...

Sheet NOK - Safespring tjenester 2025
B5: Priskalkulator 2026-05-25
B8: Kontakt Safespring | D8: Valuta
B9: Telefon: +47 35 68 88 70
B10: hello@safespring.com
B15: Safespring Kubernetes Engine
B18: Alle priser er oppgitt i NOK, eks mva.
B19: Instruksjoner: Angi ønsket antall i de fargede feltene.
B22: Kontrollplan
B23: Det første kontrollplanet er administrert, men deretter er det mulig å legge til uadministrerte kontrollplan.
B24: Produkt ID | G24: Per time | H24: Per 30 dager | I24: Antall | K24: Infrastruktur
B25: Managed Control plane | G25: =H25/720 -> 6.8055556 | H25: 4900 | K25: =ROUNDUP(I25*H25,2) -> 0
B26: Unmanaged Control plane | G26: =H26/720 -> 0 | H26: 0 | K26: =ROUNDUP(I26*H26,2) -> 0
B27: Totalt | I27: =SUM(I14:I26)&" stk." -> 0 stk. | K27: =SUM(K14:K26) -> 0
B30: Safespring Compute | IaaS
B33: Infrastruktur kan kjøres med en Open Source-lisens eller med en Windows-lisens.
B34: Alle priser er oppgitt i NOK, eks mva.
B35: Instruksjoner: Angi ønsket antall i de fargede feltene.
B38: Flavors med lokal NVMe-disk
B39: Sentral blokklagring kan kjøpes til instansene. Se "Sentral blokklagring" i prislisten.
B40: Produkt ID | C40: vCPU | D40: RAM (GB) | E40: Lokal disk (GB) | G40: Per time | H40: Per 30 dager | I40: Antall | K40: Infrastruktur
B41: FLAVOR-l2. c2 r4. 100 | C41: 2 | D41: 4 | E41: 100 | G41: =H41/720 -> 0.66666667 | H41: =C41*IAAS_vcpu_SEK+D41*IAAS_ram_SEK+E41*IAAS_nvme_SEK -> 480 | K41: =ROUNDUP(I41*H41,2) -> 0
B42: FLAVOR-l2. c2 r4. 500 | C42: 2 | D42: 4 | E42: 500 | G42: =H42/720 -> 1.2222222 | H42: =C42*IAAS_vcpu_SEK+D42*IAAS_ram_SEK+E42*IAAS_nvme_SEK -> 880 | K42: =ROUNDUP(I42*H42,2) -> 0
B43: FLAVOR-l2. c2 r4. 1000 | C43: 2 | D43: 4 | E43: 1000 | G43: =H43/720 -> 1.9166667 | H43: =C43*IAAS_vcpu_SEK+D43*IAAS_ram_SEK+E43*IAAS_nvme_SEK -> 1380 | K43: =ROUNDUP(I43*H43,2) -> 0
B44: FLAVOR-l2. c4 r8. 100 | C44: 4 | D44: 8 | E44: 100 | G44: =H44/720 -> 1.1944444 | H44: =C44*IAAS_vcpu_SEK+D44*IAAS_ram_SEK+E44*IAAS_nvme_SEK -> 860 | K44: =ROUNDUP(I44*H44,2) -> 0
B45: FLAVOR-l2. c4 r8. 500 | C45: 4 | D45: 8 | E45: 500 | G45: =H45/720 -> 1.75 | H45: =C45*IAAS_vcpu_SEK+D45*IAAS_ram_SEK+E45*IAAS_nvme_SEK -> 1260 | K45: =ROUNDUP(I45*H45,2) -> 0
B46: FLAVOR-l2. c4 r8. 1000 | C46: 4 | D46: 8 | E46: 1000 | G46: =H46/720 -> 2.4444444 | H46: =C46*IAAS_vcpu_SEK+D46*IAAS_ram_SEK+E46*IAAS_nvme_SEK -> 1760 | K46: =ROUNDUP(I46*H46,2) -> 0
B47: FLAVOR-l2. c8 r16. 100 | C47: 8 | D47: 16 | E47: 100 | G47: =H47/720 -> 2.25 | H47: =C47*IAAS_vcpu_SEK+D47*IAAS_ram_SEK+E47*IAAS_nvme_SEK -> 1620 | K47: =ROUNDUP(I47*H47,2) -> 0
B48: FLAVOR-l2. c8 r16. 500 | C48: 8 | D48: 16 | E48: 500 | G48: =H48/720 -> 2.8055556 | H48: =C48*IAAS_vcpu_SEK+D48*IAAS_ram_SEK+E48*IAAS_nvme_SEK -> 2020 | K48: =ROUNDUP(I48*H48,2) -> 0
B49: FLAVOR-l2. c8 r16. 1000 | C49: 8 | D49: 16 | E49: 1000 | G49: =H49/720 -> 3.5 | H49: =C49*IAAS_vcpu_SEK+D49*IAAS_ram_SEK+E49*IAAS_nvme_SEK -> 2520 | K49: =ROUNDUP(I49*H49,2) -> 0
B50: FLAVOR-l2. c16 r32. 100 | C50: 16 | D50: 32 | E50: 100 | G50: =H50/720 -> 4.3611111 | H50: =C50*IAAS_vcpu_SEK+D50*IAAS_ram_SEK+E50*IAAS_nvme_SEK -> 3140 | K50: =ROUNDUP(I50*H50,2) -> 0
B51: FLAVOR-l2. c16 r32. 500 | C51: 16 | D51: 32 | E51: 500 | G51: =H51/720 -> 4.9166667 | H51: =C51*IAAS_vcpu_SEK+D51*IAAS_ram_SEK+E51*IAAS_nvme_SEK -> 3540 | K51: =ROUNDUP(I51*H51,2) -> 0
B52: FLAVOR-l2. c16 r32. 1000 | C52: 16 | D52: 32 | E52: 1000 | G52: =H52/720 -> 5.6111111 | H52: =C52*IAAS_vcpu_SEK+D52*IAAS_ram_SEK+E52*IAAS_nvme_SEK -> 4040 | K52: =ROUNDUP(I52*H52,2) -> 0
... B54: FLAVOR-l2. c32 r64. 1000 | C54: 32 | D54: 64 | E54: 1000 | G54: =H54/720 -> 9.8333333 | H54: =C54*IAAS_vcpu_SEK+D54*IAAS_ram_SEK+E54*IAAS_nvme_SEK -> 7080 | K54: =ROUNDUP(I54*H54,2) -> 0
B55: Totalt | C55: =SUMPRODUCT(C41:C54,I41:I54)&" stk." -> 0 stk. | D55: {=SUM(D41:D54*I41:I54)&" GB"} -> 0 GB | E55: {=SUM(E41:E54*I41:I54)&" GB"} -> 0 GB | I55: =SUM(I41:I54)&" stk." -> 0 stk. | K55: =SUM(K41:K54) -> 0
B59: Flavors uten lokal disk
B60: Sentral blokklagring kan kjøpes til instansene. Se "Sentral blokklagring" i prislisten.
B61: Produkt ID | C61: vCPU | D61: RAM (GB) | E61: Lokal disk (GB) | G61: Per time | H61: Per 30 dager | I61: Antall | K61: Infrastruktur
B62: FLAVOR-b2. c1 r2 | C62: 1 | D62: 2 | E62: 0 | G62: ='SEK - Safesprings tjänster 2025'!G62 -> 0.26388889 | H62: =C62*IAAS_vcpu_SEK+D62*IAAS_ram_SEK+E62*IAAS_nvme_SEK -> 190 | K62: =ROUNDUP(I62*H62,2) -> 0
B63: FLAVOR-b2. c1 r4 | C63: 1 | D63: 4 | E63: 0 | G63: ='SEK - Safesprings tjänster 2025'!G63 -> 0.41666667 | H63: =C63*IAAS_vcpu_SEK+D63*IAAS_ram_SEK+E63*IAAS_nvme_SEK -> 300 | K63: =ROUNDUP(I63*H63,2) -> 0
B64: FLAVOR-b2. c2 r4 | C64: 2 | D64: 4 | E64: 0 | G64: ='SEK - Safesprings tjänster 2025'!G64 -> 0.52777778 | H64: =C64*IAAS_vcpu_SEK+D64*IAAS_ram_SEK+E64*IAAS_nvme_SEK -> 380 | K64: =ROUNDUP(I64*H64,2) -> 0
B65: FLAVOR-b2. c2 r8 | C65: 2 | D65: 8 | E65: 0 | G65: ='SEK - Safesprings tjänster 2025'!G65 -> 0.83333333 | H65: =C65*IAAS_vcpu_SEK+D65*IAAS_ram_SEK+E65*IAAS_nvme_SEK -> 600 | K65: =ROUNDUP(I65*H65,2) -> 0
B66: FLAVOR-b2 .c4 r8 | C66: 4 | D66: 8 | E66: 0 | G66: ='SEK - Safesprings tjänster 2025'!G66 -> 1.0555556 | H66: =C66*IAAS_vcpu_SEK+D66*IAAS_ram_SEK+E66*IAAS_nvme_SEK -> 760 | K66: =ROUNDUP(I66*H66,2) -> 0
B67: FLAVOR-b2. c4 r16 | C67: 4 | D67: 16 | E67: 0 | G67: ='SEK - Safesprings tjänster 2025'!G67 -> 1.6666667 | H67: =C67*IAAS_vcpu_SEK+D67*IAAS_ram_SEK+E67*IAAS_nvme_SEK -> 1200 | K67: =ROUNDUP(I67*H67,2) -> 0
B68: FLAVOR-b2. c8 r16 | C68: 8 | D68: 16 | E68: 0 | G68: ='SEK - Safesprings tjänster 2025'!G68 -> 2.1111111 | H68: =C68*IAAS_vcpu_SEK+D68*IAAS_ram_SEK+E68*IAAS_nvme_SEK -> 1520 | K68: =ROUNDUP(I68*H68,2) -> 0
B69: FLAVOR-b2. c8 r32 | C69: 8 | D69: 32 | E69: 0 | G69: ='SEK - Safesprings tjänster 2025'!G69 -> 3.3333333 | H69: =C69*IAAS_vcpu_SEK+D69*IAAS_ram_SEK+E69*IAAS_nvme_SEK -> 2400 | K69: =ROUNDUP(I69*H69,2) -> 0
B70: FLAVOR-b2. c16 r32 | C70: 16 | D70: 32 | E70: 0 | G70: ='SEK - Safesprings tjänster 2025'!G70 -> 4.2222222 | H70: =C70*IAAS_vcpu_SEK+D70*IAAS_ram_SEK+E70*IAAS_nvme_SEK -> 3040 | K70: =ROUNDUP(I70*H70,2) -> 0
B71: FLAVOR-b2. c16 r64 | C71: 16 | D71: 64 | E71: 0 | G71: ='SEK - Safesprings tjänster 2025'!G71 -> 6.6666667 | H71: =C71*IAAS_vcpu_SEK+D71*IAAS_ram_SEK+E71*IAAS_nvme_SEK -> 4800 | K71: =ROUNDUP(I71*H71,2) -> 0
B72: Totalt | C72: {=SUM(C62:C71*I62:I71)} -> 0 | D72: {=SUM(D62:D71*I62:I71)} -> 0 | I72: =SUM(I62:I71)&" stk." -> 0 stk. | K72: =SUM(K62:K71) -> 0
B76: Flavors med GPU
B77: Sentral blokklagring kan kjøpes til instansene. Se "Sentral blokklagring" i prislisten.
B78: Produkt ID | C78: vCPU | D78: RAM (GB) | E78: Lokal disk (GB) | F78: Nvidia | G78: Per time | H78: Per 30 dager | I78: Antall instanser | K78: Infrastruktur
B79: FLAVOR-l2.c4r16.125.gA2 | C79: 4 | D79: 16 | E79: 125 | F79: A2 | G79: =H79/720 -> 4.6458333 | H79: =C79*IAAS_vcpu_SEK+D79*IAAS_ram_SEK+E79*IAAS_nvme_SEK+1*IAAS_GPU_A2_SEK -> 3345 | K79: =ROUNDUP(I79*H79,2) -> 0
B80: FLAVOR-l2.c8r32.250.gA2 | C80: 8 | D80: 32 | E80: 250 | F80: A2 | G80: =H80/720 -> 6.4861111 | H80: =C80*IAAS_vcpu_SEK+D80*IAAS_ram_SEK+E80*IAAS_nvme_SEK+1*IAAS_GPU_A2_SEK -> 4670 | K80: =ROUNDUP(I80*H80,2) -> 0
B81: FLAVOR-b2.c4r8.gA2 | C81: 4 | D81: 8 | E81: 0 | F81: A2 | G81: =H81/720 -> 3.8611111 | H81: =C81*IAAS_vcpu_SEK+D81*IAAS_ram_SEK+E81*IAAS_nvme_SEK+1*IAAS_GPU_A2_SEK -> 2780 | K81: =ROUNDUP(I81*H81,2) -> 0
B82: FLAVOR-b2.c8r16.gA2 | C82: 8 | D82: 16 | E82: 0 | F82: A2 | G82: =H82/720 -> 4.9166667 | H82: =C82*IAAS_vcpu_SEK+D82*IAAS_ram_SEK+E82*IAAS_nvme_SEK+1*IAAS_GPU_A2_SEK -> 3540 | K82: =ROUNDUP(I82*H82,2) -> 0
B83: FLAVOR-b2.c32.r192.gH100 | C83: 32 | D83: 192 | E83: 0 | F83: H100 | G83: =H83/720 -> 33.366667 | H83: =C83*IAAS_vcpu_SEK+D83*IAAS_ram_SEK+E83*IAAS_nvme_SEK+1*IAAS_GPU_H100_SEK -> 24024 | K83: =ROUNDUP(I83*H83,2) -> 0
B84: Totalt | C84: =SUMPRODUCT(C79:C83,I79:I83)&" stk." -> 0 stk. | D84: =SUMPRODUCT(D79:D83,I79:I83)&" GB" -> 0 GB | E84: =SUMPRODUCT(E79:E83,I79:I83)&" GB" -> 0 GB | I84: =SUM(I79:I83)&" stk." -> 0 stk. | K84: =SUM(K79:K83) -> 0
B88: Sentral blokklagring
B89: Sentral blokklagring gir tre kopier av dataene distribuert i en robust CEPH-klynge.
B90: Produkt ID | C90: Beskrivelse | G90: Per time | H90: Per 30 dager | I90: Antall (GB) | K90: Lagring
B91: VOLUME-large | C91: HDD-backed 3-replica Ceph | G91: =H91/720 -> 0.0016666667 | H91: =VOLUME_large_SEK -> 1.2 | K91: =ROUNDUP(I91*H91,2) -> 0
B92: VOLUME-fast | C92: SSD-backed 3-replica Ceph | G92: =H92/720 -> 0.005 | H92: =VOLUME_fast_SEK -> 3.6 | K92: =ROUNDUP(I92*H92,2) -> 0
B93: VOLUME-snapshot | C93: Snapshot of image | G93: =H93/720 -> 0.0016666667 | H93: =VOLUME_large_SEK -> 1.2 | K93: =ROUNDUP(I93*H93,2) -> 0
B94: Totalt | I94: =SUM(I91:I93)&" GB" -> 0 GB | K94: =SUM(K91:K93) -> 0
B97: Safespring Storage | S3
B100: Kontakt oss for rabatter på større lagringsmengder. Prismodell basert på antall lagrede TB per måned.
B101: Alle priser er oppgitt i NOK, eks mva
B102: Instruksjoner: Angi ønsket antall i de fargede feltene.
B104: Produkt ID | G104: Per TB i 30 dager | I104: Antall (TB) | K104: Storage
B105: S3-archive | C105: Tilpasset større lagringsvolumer over lengre tid. | G105: =S3_archive.50_SEK -> 350 | K105: =I105*G105 -> 0
B106: S3-storage | C106: Tilpasset applikasjoner som aktivt bruker S3-protokollen. | G106: =S3_storage50_SEK -> 500 | K106: =I106*G106 -> 0
B107: Totalt | K107: =SUM(K105:K106) -> 0
B110: Safespring Backup | SP
B113: Cloud backup-løsning for on-prem eller skyservere basert på Spectrum Protect (TSM).
B114: Alle priser er oppgitt i NOK, eks mva.
B115: Instruksjoner: Angi ønsket antall i de fargede feltene.
B117: Produkt ID | E117: Fast månedlig pris | G117: Per GB i 30 dager | I117: Antall (GB) | J117: Deduplisering 1 | K117: Backup
B118: BAAS-on.demand 2 | E118: N/A | G118: =BAAS_on.demand_SEK -> 2.45 | J118: N/A | K118: =ROUNDUP(I118*G118,2) -> 0
B119: BAAS-small 3 | E119: 5500 | G119: =BAAS_small_SEK -> 1.75 | J119: 0.75 | K119: =IF(I119>0,$E$119+$G$119*MAX(0,I119*(1-$J$119)-1000),0) -> 0
B120: BAAS-large 4 | E120: 9500 | G120: =BAAS_large_SEK -> 0.92 | J120: 0.75 | K120: =IF(I120>0,$E$120+($G$120*(I120*(1-$J$120))),0) -> 0
B121: Totalt | I121: =SUM(I118:I120)&" GB" -> 0 GB | K121: =SUM(K118:K120) -> 0
B125: Nettverk og programvare
B128: Alle priser er oppgitt i NOK, eks mva.
B131: Nettverk
B132: Safespring tilbyr flere nettverkstjenester.
B133: Produkt ID | C133: Type | E133: Beskrivelse | J133: Fakturering pr | K133: Per måned
B134: NET-publicv4 | C134: IPv4 | E134: Offentlig | J134: IP-adresse | K134: =NET_publicv4_SEK -> 25
B135: NET-publicv6 | C135: IPv6 | E135: Offentlig | J135: N/A | K135: =NET_publicv6_SEK -> 0
B136: NET-ingress | C136: Datatrafikk | J136: GB | K136: =NET_ingress_SEK -> 0
B137: NET-egress | C137: Datatrafikk | J137: GB | K137: =NET_egress_SEK -> 0
B138: NET-mgn.slb | C138: Managed SLB (ElasticIP) | E138: Lastbalansere som krever egne instanser | J138: Instans | K138: Tilbud
B139: NET-rdns | C139: Reverse DNS names | J139: N/A | K139: =NET_rdns_SEK -> 0
B140: NET-byoip | C140: Bring your own IP prefixes | J140: N/A | K140: 0
B144: Programvare og lisenser
B145: Safespring tilbyr flere programvarer og lisenser.
B146: Produkt ID | E146: Beskrivelse | J146: Fakturering pr | K146: Per måned
B147: SW-win.ser.2022 | E147: Microsoft Windows Server | J147: vCPU | K147: =SW_win.ser.201X_SEK -> 175
B148: SW-ms.sql.ser | E148: Microsoft SQL Server Standard | J148: vCPU | K148: =SW_ms.sql.ser_SEK -> 1229
B149: SW-ms.sql.ser.ent | E149: Microsoft SQL Server Enterprise | J149: vCPU | K149: =SW_ms.sql.ser.ent_SEK -> 4766
B153: Partnertjenester
...

Sheet EUR - Safespring services 2021
B5: Price calculator 2022-01-04
B8: Contact Safespring | D8: Currency
B9: Phone: +46 855 10 73 56
B10: sales@safespring.com
D11: ="1 SEK = "&EUR&" EUR" -> 1 SEK = 0,094 EUR
B15: Safespring Compute
B18: Infrastructure as a service can run on a open source license or with a Windows license.
B19: All prices are in EUR, excluding VAT.
B20: Instructions: Enter the desired amount in the colored fields
B23: Instances with central block storage
B24: Product ID | C24: vCPU | D24: RAM (GB) | E24: Storage (GB) | G24: Hourly | H24: Monthly (30 days) | I24: Instances | K24: Infrastructure
B25: INSTANCE-b.tiny | C25: 1 | D25: 1 | E25: 40 | G25: =H25/720 -> 0.036425 | H25: =C25*IAAS_vcpu_EUR+D25*IAAS_ram_EUR+E25*IAAS_ssd_EUR -> 26.226 | J25: Instances | K25: =ROUNDUP(I25*H25,2) -> 0
B26: INSTANCE-b.small | C26: 1 | D26: 2 | E26: 40 | G26: =H26/720 -> 0.043605556 | H26: =C26*IAAS_vcpu_EUR+D26*IAAS_ram_EUR+E26*IAAS_ssd_EUR -> 31.396 | J26: =J25 -> Instances | K26: =ROUNDUP(I26*H26,2) -> 0
B27: INSTANCE-b.medium | C27: 2 | D27: 4 | E27: 40 | G27: =H27/720 -> 0.068411111 | H27: =C27*IAAS_vcpu_EUR+D27*IAAS_ram_EUR+E27*IAAS_ssd_EUR -> 49.256 | J27: =J26 -> Instances | K27: =ROUNDUP(I27*H27,2) -> 0
B28: INSTANCE-b.large | C28: 4 | D28: 8 | E28: 40 | G28: =H28/720 -> 0.11802222 | H28: =C28*IAAS_vcpu_EUR+D28*IAAS_ram_EUR+E28*IAAS_ssd_EUR -> 84.976 | J28: =J27 -> Instances | K28: =ROUNDUP(I28*H28,2) -> 0
B29: INSTANCE-b.xlarge | C29: 8 | D29: 16 | E29: 40 | G29: =H29/720 -> 0.21724444 | H29: =C29*IAAS_vcpu_EUR+D29*IAAS_ram_EUR+E29*IAAS_ssd_EUR -> 156.416 | J29: =J28 -> Instances | K29: =ROUNDUP(I29*H29,2) -> 0
B30: INSTANCE-b.2xlarge | C30: 16 | D30: 32 | E30: 40 | G30: =H30/720 -> 0.41568889 | H30: =C30*IAAS_vcpu_EUR+D30*IAAS_ram_EUR+E30*IAAS_ssd_EUR -> 299.296 | J30: =J29 -> Instances | K30: =ROUNDUP(I30*H30,2) -> 0
B31: INSTANCE-m.small | C31: 1 | D31: 4 | E31: 40 | G31: =H31/720 -> 0.057966667 | H31: =C31*IAAS_vcpu_EUR+D31*IAAS_ram_EUR+E31*IAAS_ssd_EUR -> 41.736 | J31: =J30 -> Instances | K31: =ROUNDUP(I31*H31,2) -> 0
B32: INSTANCE-m.medium | C32: 2 | D32: 8 | E32: 40 | G32: =H32/720 -> 0.097133333 | H32: =C32*IAAS_vcpu_EUR+D32*IAAS_ram_EUR+E32*IAAS_ssd_EUR -> 69.936 | J32: =J31 -> Instances | K32: =ROUNDUP(I32*H32,2) -> 0
B33: INSTANCE-m.large | C33: 4 | D33: 16 | E33: 40 | G33: =H33/720 -> 0.17546667 | H33: =C33*IAAS_vcpu_EUR+D33*IAAS_ram_EUR+E33*IAAS_ssd_EUR -> 126.336 | J33: =J32 -> Instances | K33: =ROUNDUP(I33*H33,2) -> 0
B34: INSTANCE-m.xlarge | C34: 8 | D34: 32 | E34: 40 | G34: =H34/720 -> 0.33213333 | H34: =C34*IAAS_vcpu_EUR+D34*IAAS_ram_EUR+E34*IAAS_ssd_EUR -> 239.136 | J34: =J33 -> Instances | K34: =ROUNDUP(I34*H34,2) -> 0
B35: INSTANCE-m.2xlarge | C35: 16 | D35: 64 | E35: 40 | G35: =H35/720 -> 0.64546667 | H35: =C35*IAAS_vcpu_EUR+D35*IAAS_ram_EUR+E35*IAAS_ssd_EUR -> 464.736 | J35: =J34 -> Instances | K35: =ROUNDUP(I35*H35,2) -> 0
B36: INSTANCE-m.4xlarge | C36: 32 | D36: 128 | E36: 40 | G36: =H36/720 -> 1.2721333 | H36: =C36*IAAS_vcpu_EUR+D36*IAAS_ram_EUR+E36*IAAS_ssd_EUR -> 915.936 | J36: =J35 -> Instances | K36: =ROUNDUP(I36*H36,2) -> 0
B37: INSTANCE-m.8xlarge | C37: 64 | D37: 256 | E37: 40 | G37: =H37/720 -> 2.5254667 | H37: =C37*IAAS_vcpu_EUR+D37*IAAS_ram_EUR+E37*IAAS_ssd_EUR -> 1818.336 | J37: =J36 -> Instances | K37: =ROUNDUP(I37*H37,2) -> 0
B38: Total | C38: {=SUM(C25:C37*I25:I37)} -> 0 | D38: {=SUM(D25:D37*I25:I37)} -> 0 | E38: {=SUM(E25:E37*I25:I37)} -> 0 | I38: =SUM(I25:I37) -> 0 | K38: =SUM(K25:K37)&" €" -> 0 €
B41: Instances with local storage (NVMe)
B42: Product ID | C42: vCPU | D42: RAM (GB) | E42: NVME (GB) | G42: Hourly | H42: Monthly (30 days) | I42: Instances | K42: Infrastructure
B43: INSTANCE-lb.tiny | C43: 1 | D43: 1 | E43: 10 | G43: =H43/720 -> 0.018930556 | H43: =C43*IAAS_vcpu_EUR+D43*IAAS_ram_EUR+E43*IAAS_nvme_EUR -> 13.63 | J43: =J37 -> Instances | K43: =ROUNDUP(I43*H43,2) -> 0
B44: INSTANCE-lb.small | C44: 1 | D44: 2 | E44: 20 | G44: =H44/720 -> 0.027416667 | H44: =C44*IAAS_vcpu_EUR+D44*IAAS_ram_EUR+E44*IAAS_nvme_EUR -> 19.74 | J44: =J43 -> Instances | K44: =ROUNDUP(I44*H44,2) -> 0
B45: INSTANCE-lb.medium.1d | C45: 2 | D45: 4 | E45: 250 | G45: =H45/720 -> 0.08225 | H45: =C45*IAAS_vcpu_EUR+D45*IAAS_ram_EUR+E45*IAAS_nvme_EUR -> 59.22 | J45: =J44 -> Instances | K45: =ROUNDUP(I45*H45,2) -> 0
B46: INSTANCE-lb.large.1d | C46: 4 | D46: 8 | E46: 250 | G46: =H46/720 -> 0.13186111 | H46: =C46*IAAS_vcpu_EUR+D46*IAAS_ram_EUR+E46*IAAS_nvme_EUR -> 94.94 | J46: =J45 -> Instances | K46: =ROUNDUP(I46*H46,2) -> 0
B47: INSTANCE-lb.xlarge.1d | C47: 8 | D47: 16 | E47: 250 | G47: =H47/720 -> 0.23108333 | H47: =C47*IAAS_vcpu_EUR+D47*IAAS_ram_EUR+E47*IAAS_nvme_EUR -> 166.38 | J47: =J46 -> Instances | K47: =ROUNDUP(I47*H47,2) -> 0
B48: INSTANCE-lb.2xlarge.1d | C48: 16 | D48: 32 | E48: 250 | G48: =H48/720 -> 0.42952778 | H48: =C48*IAAS_vcpu_EUR+D48*IAAS_ram_EUR+E48*IAAS_nvme_EUR -> 309.26 | J48: =J47 -> Instances | K48: =ROUNDUP(I48*H48,2) -> 0
B49: INSTANCE-lb.2xlarge.2d | C49: 16 | D49: 32 | E49: 500 | G49: =H49/720 -> 0.46216667 | H49: =C49*IAAS_vcpu_EUR+D49*IAAS_ram_EUR+E49*IAAS_nvme_EUR -> 332.76 | J49: =J48 -> Instances | K49: =ROUNDUP(I49*H49,2) -> 0
B50: INSTANCE-lb.2xlarge.4d | C50: 16 | D50: 32 | E50: 1000 | G50: =H50/720 -> 0.52744444 | H50: =C50*IAAS_vcpu_EUR+D50*IAAS_ram_EUR+E50*IAAS_nvme_EUR -> 379.76 | J50: =J49 -> Instances | K50: =ROUNDUP(I50*H50,2) -> 0
B51: INSTANCE-lb.4xlarge.1d | C51: 32 | D51: 64 | E51: 250 | G51: =H51/720 -> 0.82641667 | H51: =C51*IAAS_vcpu_EUR+D51*IAAS_ram_EUR+E51*IAAS_nvme_EUR -> 595.02 | J51: =J50 -> Instances | K51: =ROUNDUP(I51*H51,2) -> 0
B52: INSTANCE-lb.4xlarge.2d | C52: 32 | D52: 64 | E52: 500 | G52: =H52/720 -> 0.85905556 | H52: =C52*IAAS_vcpu_EUR+D52*IAAS_ram_EUR+E52*IAAS_nvme_EUR -> 618.52 | J52: =J47 -> Instances | K52: =ROUNDUP(I52*H52,2) -> 0
B53: INSTANCE-lb.4xlarge.4d | C53: 32 | D53: 64 | E53: 1000 | G53: =H53/720 -> 0.92433333 | H53: =C53*IAAS_vcpu_EUR+D53*IAAS_ram_EUR+E53*IAAS_nvme_EUR -> 665.52 | J53: =J52 -> Instances | K53: =ROUNDUP(I53*H53,2) -> 0
B54: INSTANCE-lm.small | C54: 1 | D54: 4 | E54: 20 | G54: =H54/720 -> 0.041777778 | H54: =C54*IAAS_vcpu_EUR+D54*IAAS_ram_EUR+E54*IAAS_nvme_EUR -> 30.08 | J54: =J53 -> Instances | K54: =ROUNDUP(I54*H54,2) -> 0
B55: INSTANCE-lm.medium.1d | C55: 2 | D55: 8 | E55: 250 | G55: =H55/720 -> 0.11097222 | H55: =C55*IAAS_vcpu_EUR+D55*IAAS_ram_EUR+E55*IAAS_nvme_EUR -> 79.9 | J55: =J54 -> Instances | K55: =ROUNDUP(I55*H55,2) -> 0
B56: INSTANCE-lm.large.1d | C56: 4 | D56: 16 | E56: 250 | G56: =H56/720 -> 0.18930556 | H56: =C56*IAAS_vcpu_EUR+D56*IAAS_ram_EUR+E56*IAAS_nvme_EUR -> 136.3 | J56: =J55 -> Instances | K56: =ROUNDUP(I56*H56,2) -> 0
B57: INSTANCE-lm.xlarge.1d | C57: 8 | D57: 32 | E57: 250 | G57: =H57/720 -> 0.34597222 | H57: =C57*IAAS_vcpu_EUR+D57*IAAS_ram_EUR+E57*IAAS_nvme_EUR -> 249.1 | J57: =J56 -> Instances | K57: =ROUNDUP(I57*H57,2) -> 0
B58: INSTANCE-lm.xlarge.2d | C58: 8 | D58: 32 | E58: 500 | G58: =H58/720 -> 0.37861111 | H58: =C58*IAAS_vcpu_EUR+D58*IAAS_ram_EUR+E58*IAAS_nvme_EUR -> 272.6 | J58: =J57 -> Instances | K58: =ROUNDUP(I58*H58,2) -> 0
B59: INSTANCE-lm.xlarge.4d | C59: 8 | D59: 32 | E59: 1000 | G59: =H59/720 -> 0.44388889 | H59: =C59*IAAS_vcpu_EUR+D59*IAAS_ram_EUR+E59*IAAS_nvme_EUR -> 319.6 | J59: =J58 -> Instances | K59: =ROUNDUP(I59*H59,2) -> 0
B60: INSTANCE-lm.2xlarge.1d | C60: 16 | D60: 64 | E60: 250 | G60: =H60/720 -> 0.65930556 | H60: =C60*IAAS_vcpu_EUR+D60*IAAS_ram_EUR+E60*IAAS_nvme_EUR -> 474.7 | J60: =J59 -> Instances | K60: =ROUNDUP(I60*H60,2) -> 0
B61: INSTANCE-lm.2xlarge.2d | C61: 16 | D61: 64 | E61: 500 | G61: =H61/720 -> 0.69194444 | H61: =C61*IAAS_vcpu_EUR+D61*IAAS_ram_EUR+E61*IAAS_nvme_EUR -> 498.2 | J61: =J60 -> Instances | K61: =ROUNDUP(I61*H61,2) -> 0
B62: INSTANCE-lm.2xlarge.4d | C62: 16 | D62: 64 | E62: 1000 | G62: =H62/720 -> 0.75722222 | H62: =C62*IAAS_vcpu_EUR+D62*IAAS_ram_EUR+E62*IAAS_nvme_EUR -> 545.2 | J62: =J61 -> Instances | K62: =ROUNDUP(I62*H62,2) -> 0
B63: INSTANCE-lm.4xlarge.1d | C63: 32 | D63: 128 | E63: 250 | G63: =H63/720 -> 1.2859722 | H63: =C63*IAAS_vcpu_EUR+D63*IAAS_ram_EUR+E63*IAAS_nvme_EUR -> 925.9 | J63: =J62 -> Instances | K63: =ROUNDUP(I63*H63,2) -> 0
B64: INSTANCE-lm.4xlarge.2d | C64: 32 | D64: 128 | E64: 500 | G64: =H64/720 -> 1.3186111 | H64: =C64*IAAS_vcpu_EUR+D64*IAAS_ram_EUR+E64*IAAS_nvme_EUR -> 949.4 | J64: =J63 -> Instances | K64: =ROUNDUP(I64*H64,2) -> 0
... B66: INSTANCE-lm.8xlarge.4d | C66: 64 | D66: 256 | E66: 1000 | G66: =H66/720 -> 2.6372222 | H66: =C66*IAAS_vcpu_EUR+D66*IAAS_ram_EUR+E66*IAAS_nvme_EUR -> 1898.8 | J66: =J65 -> Instances | K66: =ROUNDUP(I66*H66,2) -> 0
B67: Total | C67: {=SUM(C43:C66*I43:I66)} -> 0 | D67: {=SUM(D43:D66*I43:I66)} -> 0 | E67: {=SUM(E43:E66*I43:I66)} -> 0 | I67: =SUM(I43:I66) -> 0 | K67: =SUM(K43:K65) -> 0
B70: Instances with GPU and local storage (NVMe)
B71: Product ID | C71: vCPU | D71: RAM (GB) | E71: NVME (GB) | F71: GPU | G71: Hourly | H71: Monthly | I71: Instances | J71: Windows licenses | L71: Infrastructure | M71: Licenses
B72: INSTANCE-glm.large.1d | C72: 4 | D72: 16 | E72: 250 | F72: 1 | G72: =H72/720 -> 0.90736111 | H72: =C72*IAAS_vcpu_EUR+D72*IAAS_ram_EUR+E72*IAAS_nvme_EUR+F72*IAAS_gpu_EUR -> 653.3 | K72: =J61 -> Instances | L72: =ROUNDUP(I72*H72,2) -> 0 | M72: =J72*C72*SW_win.ser.201X_EUR -> 0
B73: INSTANCE-glm.xlarge.2d | C73: 8 | D73: 32 | E73: 500 | F73: 2 | G73: =H73/720 -> 1.8147222 | H73: =C73*IAAS_vcpu_EUR+D73*IAAS_ram_EUR+E73*IAAS_nvme_EUR+F73*IAAS_gpu_EUR -> 1306.6 | K73: =J62 -> Instances | L73: =ROUNDUP(I73*H73,2) -> 0 | M73: =J73*C73*SW_win.ser.201X_EUR -> 0
B74: INSTANCE-glm.2xlarge.4d | C74: 16 | D74: 64 | E74: 1000 | F74: 4 | G74: =H74/720 -> 3.6294444 | H74: =C74*IAAS_vcpu_EUR+D74*IAAS_ram_EUR+E74*IAAS_nvme_EUR+F74*IAAS_gpu_EUR -> 2613.2 | K74: =J63 -> Instances | L74: =ROUNDUP(I74*H74,2) -> 0 | M74: =J74*C74*SW_win.ser.201X_EUR -> 0
B75: INSTANCE-glm.4xlarge.8d | C75: 32 | D75: 128 | E75: 1000 | F75: 6 | G75: =H75/720 -> 5.6922222 | H75: =C75*IAAS_vcpu_EUR+D75*IAAS_ram_EUR+E75*IAAS_nvme_EUR+F75*IAAS_gpu_EUR -> 4098.4 | K75: =J64 -> Instances | L75: =ROUNDUP(I75*H75,2) -> 0 | M75: =J75*C75*SW_win.ser.201X_EUR -> 0
B76: Total | I76: =SUM(I72:I75) -> 0 | J76: =SUM(J72:J75) -> 0 | L76: =SUM(L72:L75) -> 0 | M76: =SUM(M72:M75) -> 0
B79: Bare Metal compute
B80: Product ID | C80: vCPU | D80: RAM (GB) | E80: NVME (GB) | G80: Hourly | H80: Monthly | I80: Instances | J80: Windows licenses | L80: Infrastructure | M80: Licenses
B81: INSTANCE-p1.2xlarge.16d | C81: 16 | D81: 128 | E81: 3800 | G81: =H81/720 -> 0.893 | H81: =INSTANCE_p1.2xlarge.16d_EUR -> 642.96 | K81: Instanser | L81: =ROUNDUP(I81*H81,2) -> 0 | M81: =J81*C81*SW_win.ser.201X_EUR -> 0
B82: INSTANCE-p1.4xlarge.16d | C82: 32 | D82: 256 | E82: 3800 | G82: =H82/720 -> 1.786 | H82: =INSTANCE_p1.4xlarge.16d_EUR -> 1285.92 | K82: =K81 -> Instanser | L82: =ROUNDUP(I82*H82,2) -> 0 | M82: =J82*C82*SW_win.ser.201X_EUR -> 0
B83: INSTANCE-p1.8xlarge.32d | C83: 64 | D83: 512 | E83: 7600 | G83: =H83/720 -> 3.572 | H83: =INSTANCE_p1.8xlarge.32d_EUR -> 2571.84 | K83: Instanser | L83: =ROUNDUP(I83*H83,2) -> 0 | M83: =J83*C83*SW_win.ser.201X_EUR -> 0
B84: Total | I84: =SUM(I81:I83) -> 0 | J84: =SUM(J81:J83) -> 0 | L84: =SUM(L81:L83) -> 0 | M84: =SUM(M81:M83) -> 0
B87: Extra Storage
B88: Product ID | C88: Description | E88: Hourly | F88: Per GB / Monthly | I88: Extra GB
B89: VOLUME-large | C89: HDD-backed 3-replica Ceph | E89: =F89/720 -> 0.00015666667 | F89: =VOLUME_large_EUR -> 0.1128 | J89: GB | K89: =ROUNDUP(I89*F89,2) -> 0
B90: VOLUME-fast | C90: SSD-backed 3-replica Ceph | E90: =F90/720 -> 0.00047 | F90: =VOLUME_fast_EUR -> 0.3384 | J90: GB | K90: =ROUNDUP(I90*F90,2) -> 0
B91: Total | I91: =SUM(I89:I90)&" GB" -> 0 GB | K91: =SUM(K89:K90) -> 0
B95: Safespring Storage
B98: Object storage with S3 standard.
B99: Price model based on the amount of terabyte stored at Safespring Storage
B100: Instructions: Enter the desired amount in the colored fields
B102: Product ID | C102: Amount of TB | D102: Per TB/monthly | H102: Amount of TB | M102: Storage
B103: S3-storage | E103: {=_xlfn.IFS(H103<50,D104,H103<100,D105,H103<500,D106,H103<1000,D107,H103>999,D108)} -> 32.9 | H103: 0 | I103: TB | M103: {=_xlfn.IFS(H103<1000,ROUNDUP(H103*E103,2),H103>999,E103)} -> 0
B104: S3-storage | C104: 0 - 49 | D104: =S3_storage.50_EUR -> 32.9
B105: S3-storage | C105: 50 - 99 | D105: =S3_storage.100_EUR -> 25.38
B106: S3-storage | C106: 100 - 499 | D106: =S3_storage.500_EUR -> 18.8
B107: S3-storage | C107: 500 - 999 | D107: =S3_storage.1000_EUR -> 17.39
B108: S3-storage | C108: 1000 - | D108: =S3_storage.quote_EUR -> Request a quote
B109: Total | M109: =M103 -> 0
B111: Product ID | C111: Amount of TB | D111: Per TB/monthly | H111: Amount of TB
B112: S3-archive | E112: {=_xlfn.IFS(H112<50,D113,H112<100,D114,H112<500,D115,H112<1000,D116,H112>999,D117)} -> 32.9 | H112: 0 | I112: TB | M112: {=_xlfn.IFS(H112<1000,ROUNDUP(H112*E112,2),H112>999,E112)} -> 0
B113: S3-archive | C113: 0 - 49 | D113: =S3_archive.50_EUR -> 32.9
B114: S3-archive | C114: 50 - 99 | D114: =S3_archive.100_EUR -> 25.38
B115: S3-archive | C115: 100 - 499 | D115: =S3_archive.500_EUR -> 18.8
B116: S3-archive | C116: 500 - 999 | D116: =S3_archive.1000_EUR -> 17.39
B117: S3-archive | C117: 1000 - | D117: =S3_archive.quote_EUR -> Request a quote
B118: Total | M118: =M112 -> 0
B122: Safespring Backup
B125: Cloud backup solution for on-prem or cloud servers based on Spectrum Protect.
B126: All prices are in EUR, excluding VAT.
B127: Instructions: Enter the desired amount in the colored fields
B129: Product ID | D129: Monthly fee | F129: Per GB/month | H129: Antal GB | J129: Deduplication* | M129: Pris
B130: BAAS-on.demand ** | D130: N/A | F130: =BAAS_on.demand_EUR -> 0.2303 | H130: 0 | I130: GB | J130: N/A | M130: =ROUNDUP(H130*F130,2) -> 0
B131: BAAS-small **** | D131: =BAAS_small.fee_EUR -> 517 | F131: =BAAS_small_EUR -> 0.1645 | H131: 0 | I131: GB | J131: 0.75 | M131: =IF(H131>0,IF(SUM($D$131+($F$131*((H131*(1-$J$131))-1000)))<=D131,$D$131,$D$131+($F$131*((H131*(1-$J$131))-1000))),0) -> 0
B132: BAAS-large *** | D132: =BAAS_large.fee_EUR -> 893 | F132: =BAAS_large_EUR -> 0.08648 | H132: 0 | I132: GB | J132: 0.75 | M132: =IF(H132>0,$D$132+($F$132*(H132*(1-$J$132))),0) -> 0
B133: Total | H133: =SUM(H130:H132)&" GB" -> 0 GB | M133: =SUM(M130:M132) -> 0
B135: * Deduplication is a data reduction done in the service. Depending on the data, it usually varies between 45% -90%
B136: ** The price is per protected GB on the client.
...

Sheet NOK - Safesprings tjeneste 2021
B5: Priskalkulator 04.01.2022
B8: Kontakt Safespring | D8: Valuta
B9: Telefon: +47 35 68 88 70
B10: sales@safespring.se
D11: ="1 SEK = "&NOK&" NOK" -> 1 SEK = 1 NOK
B15: Safespring Compute
B18: Infrastruktur kan kjøres med en gratis opensource-lisens eller med en Windows-lisens.
B19: Alle priser er oppgitt i NOK, eksklusiv mva.
B20: Instruksjoner: Angi ønsket antall i de fargede feltene.
B23: Instanser med sentral blokklagring
B24: Produkt ID | C24: vCPU | D24: RAM (GB) | E24: Disk (GB) | G24: Per time | H24: Per måned | I24: Antall instanser | K24: Infrastruktur
B25: INSTANCE-b.tiny | C25: 1 | D25: 1 | E25: 40 | G25: =H25/720 -> 0.3875 | H25: =C25*IAAS_vcpu_SEK+D25*IAAS_ram_SEK+E25*IAAS_ssd_SEK -> 279 | J25: Instanser | K25: =ROUNDUP(I25*H25,2) -> 0
B26: INSTANCE-b.small | C26: 1 | D26: 2 | E26: 40 | G26: =H26/720 -> 0.46388889 | H26: =C26*IAAS_vcpu_SEK+D26*IAAS_ram_SEK+E26*IAAS_ssd_SEK -> 334 | J26: Instanser | K26: =ROUNDUP(I26*H26,2) -> 0
B27: INSTANCE-b.medium | C27: 2 | D27: 4 | E27: 40 | G27: =H27/720 -> 0.72777778 | H27: =C27*IAAS_vcpu_SEK+D27*IAAS_ram_SEK+E27*IAAS_ssd_SEK -> 524 | J27: Instanser | K27: =ROUNDUP(I27*H27,2) -> 0
B28: INSTANCE-b.large | C28: 4 | D28: 8 | E28: 40 | G28: =H28/720 -> 1.2555556 | H28: =C28*IAAS_vcpu_SEK+D28*IAAS_ram_SEK+E28*IAAS_ssd_SEK -> 904 | J28: Instanser | K28: =ROUNDUP(I28*H28,2) -> 0
B29: INSTANCE-b.xlarge | C29: 8 | D29: 16 | E29: 40 | G29: =H29/720 -> 2.3111111 | H29: =C29*IAAS_vcpu_SEK+D29*IAAS_ram_SEK+E29*IAAS_ssd_SEK -> 1664 | J29: Instanser | K29: =ROUNDUP(I29*H29,2) -> 0
B30: INSTANCE-b.2xlarge | C30: 16 | D30: 32 | E30: 40 | G30: =H30/720 -> 4.4222222 | H30: =C30*IAAS_vcpu_SEK+D30*IAAS_ram_SEK+E30*IAAS_ssd_SEK -> 3184 | J30: Instanser | K30: =ROUNDUP(I30*H30,2) -> 0
B31: INSTANCE-m.small | C31: 1 | D31: 4 | E31: 40 | G31: =H31/720 -> 0.61666667 | H31: =C31*IAAS_vcpu_SEK+D31*IAAS_ram_SEK+E31*IAAS_ssd_SEK -> 444 | J31: Instanser | K31: =ROUNDUP(I31*H31,2) -> 0
B32: INSTANCE-m.medium | C32: 2 | D32: 8 | E32: 40 | G32: =H32/720 -> 1.0333333 | H32: =C32*IAAS_vcpu_SEK+D32*IAAS_ram_SEK+E32*IAAS_ssd_SEK -> 744 | J32: Instanser | K32: =ROUNDUP(I32*H32,2) -> 0
B33: INSTANCE-m.large | C33: 4 | D33: 16 | E33: 40 | G33: =H33/720 -> 1.8666667 | H33: =C33*IAAS_vcpu_SEK+D33*IAAS_ram_SEK+E33*IAAS_ssd_SEK -> 1344 | J33: Instanser | K33: =ROUNDUP(I33*H33,2) -> 0
B34: INSTANCE-m.xlarge | C34: 8 | D34: 32 | E34: 40 | G34: =H34/720 -> 3.5333333 | H34: =C34*IAAS_vcpu_SEK+D34*IAAS_ram_SEK+E34*IAAS_ssd_SEK -> 2544 | J34: Instanser | K34: =ROUNDUP(I34*H34,2) -> 0
B35: INSTANCE-m.2xlarge | C35: 16 | D35: 64 | E35: 40 | G35: =H35/720 -> 6.8666667 | H35: =C35*IAAS_vcpu_SEK+D35*IAAS_ram_SEK+E35*IAAS_ssd_SEK -> 4944 | J35: Instanser | K35: =ROUNDUP(I35*H35,2) -> 0
B36: INSTANCE-m.4xlarge | C36: 32 | D36: 128 | E36: 40 | G36: =H36/720 -> 13.533333 | H36: =C36*IAAS_vcpu_SEK+D36*IAAS_ram_SEK+E36*IAAS_ssd_SEK -> 9744 | J36: Instanser | K36: =ROUNDUP(I36*H36,2) -> 0
B37: INSTANCE-m.8xlarge | C37: 64 | D37: 256 | E37: 40 | G37: =H37/720 -> 26.866667 | H37: =C37*IAAS_vcpu_SEK+D37*IAAS_ram_SEK+E37*IAAS_ssd_SEK -> 19344 | J37: Instanser | K37: =ROUNDUP(I37*H37,2) -> 0
B38: Totalt | C38: {=SUM(C25:C37*I25:I37)} -> 0 | D38: {=SUM(D25:D37*I25:I37)} -> 0 | E38: {=SUM(E25:E37*I25:I37)} -> 0 | I38: =SUM(I25:I37)&" st" -> 0 st | K38: =SUM(K25:K35) -> 0
B41: Instanser med lokal lagring (NVMe-disk)
B42: Produkt ID | C42: vCPU | D42: RAM (GB) | E42: Disk (GB) | G42: Per time | H42: Per måned | I42: Antall instanser | K42: Infrastruktur
B43: INSTANCE-lb.tiny | C43: 1 | D43: 1 | E43: 10 | G43: =H43/720 -> 0.20138889 | H43: =C43*IAAS_vcpu_SEK+D43*IAAS_ram_SEK+E43*IAAS_nvme_SEK -> 145 | J43: Instanser | K43: =ROUNDUP(I43*H43,2) -> 0
B44: INSTANCE-lb.small | C44: 1 | D44: 2 | E44: 20 | G44: =H44/720 -> 0.29166667 | H44: =C44*IAAS_vcpu_SEK+D44*IAAS_ram_SEK+E44*IAAS_nvme_SEK -> 210 | J44: Instanser | K44: =ROUNDUP(I44*H44,2) -> 0
B45: INSTANCE-lb.medium.1d | C45: 2 | D45: 4 | E45: 250 | G45: =H45/720 -> 0.875 | H45: =C45*IAAS_vcpu_SEK+D45*IAAS_ram_SEK+E45*IAAS_nvme_SEK -> 630 | J45: Instanser | K45: =ROUNDUP(I45*H45,2) -> 0
B46: INSTANCE-lb.large.1d | C46: 4 | D46: 8 | E46: 250 | G46: =H46/720 -> 1.4027778 | H46: =C46*IAAS_vcpu_SEK+D46*IAAS_ram_SEK+E46*IAAS_nvme_SEK -> 1010 | J46: Instanser | K46: =ROUNDUP(I46*H46,2) -> 0
B47: INSTANCE-lb.xlarge.1d | C47: 8 | D47: 16 | E47: 250 | G47: =H47/720 -> 2.4583333 | H47: =C47*IAAS_vcpu_SEK+D47*IAAS_ram_SEK+E47*IAAS_nvme_SEK -> 1770 | J47: Instanser | K47: =ROUNDUP(I47*H47,2) -> 0
B48: INSTANCE-lb.2xlarge.1d | C48: 16 | D48: 32 | E48: 250 | G48: =H48/720 -> 4.5694444 | H48: =C48*IAAS_vcpu_SEK+D48*IAAS_ram_SEK+E48*IAAS_nvme_SEK -> 3290 | J48: Instanser | K48: =ROUNDUP(I48*H48,2) -> 0
B49: INSTANCE-lb.2xlarge.2d | C49: 16 | D49: 32 | E49: 500 | G49: =H49/720 -> 4.9166667 | H49: =C49*IAAS_vcpu_SEK+D49*IAAS_ram_SEK+E49*IAAS_nvme_SEK -> 3540 | J49: Instanser | K49: =ROUNDUP(I49*H49,2) -> 0
B50: INSTANCE-lb.2xlarge.4d | C50: 16 | D50: 32 | E50: 1000 | G50: =H50/720 -> 5.6111111 | H50: =C50*IAAS_vcpu_SEK+D50*IAAS_ram_SEK+E50*IAAS_nvme_SEK -> 4040 | J50: Instanser | K50: =ROUNDUP(I50*H50,2) -> 0
B51: INSTANCE-lb.4xlarge.1d | C51: 32 | D51: 64 | E51: 250 | G51: =H51/720 -> 8.7916667 | H51: =C51*IAAS_vcpu_SEK+D51*IAAS_ram_SEK+E51*IAAS_nvme_SEK -> 6330 | J51: Instanser | K51: =ROUNDUP(I51*H51,2) -> 0
B52: INSTANCE-lb.4xlarge.2d | C52: 32 | D52: 64 | E52: 500 | G52: =H52/720 -> 9.1388889 | H52: =C52*IAAS_vcpu_SEK+D52*IAAS_ram_SEK+E52*IAAS_nvme_SEK -> 6580 | J52: Instanser | K52: =ROUNDUP(I52*H52,2) -> 0
B53: INSTANCE-lb.4xlarge.4d | C53: 32 | D53: 64 | E53: 1000 | G53: =H53/720 -> 9.8333333 | H53: =C53*IAAS_vcpu_SEK+D53*IAAS_ram_SEK+E53*IAAS_nvme_SEK -> 7080 | J53: Instanser | K53: =ROUNDUP(I53*H53,2) -> 0
B54: INSTANCE-lm.small | C54: 1 | D54: 4 | E54: 20 | G54: =H54/720 -> 0.44444444 | H54: =C54*IAAS_vcpu_SEK+D54*IAAS_ram_SEK+E54*IAAS_nvme_SEK -> 320 | J54: Instanser | K54: =ROUNDUP(I54*H54,2) -> 0
... B66: INSTANCE-lm.8xlarge.4d | C66: 64 | D66: 256 | E66: 1000 | G66: =H66/720 -> 28.055556 | H66: =C66*IAAS_vcpu_SEK+D66*IAAS_ram_SEK+E66*IAAS_nvme_SEK -> 20200 | J66: Instanser | K66: =ROUNDUP(I66*H66,2) -> 0
B67: Totalt | C67: {=SUM(C43:C66*I43:I66)} -> 0 | D67: {=SUM(D43:D66*I43:I66)} -> 0 | E67: {=SUM(E43:E66*I43:I66)} -> 0 | I67: =SUM(I43:I66)&" st" -> 0 st | K67: =SUM(K43:K65) -> 0
B70: Instanser med GPU og lokal lagring (NVME-disk)
B71: Produkt ID | C71: CPU (p) core | D71: RAM (GB) | E71: NVME (GB) | F71: GPU | G71: Per time | H71: Per måned | I71: Antall instanser | J71: Windows-lisenser | L71: Infrastruktur | M71: Lisenser
B72: INSTANCE-glm.large.1d | C72: 4 | D72: 16 | E72: 250 | F72: 1 | G72: =H72/720 -> 9.6527778 | H72: =C72*IAAS_vcpu_SEK+D72*IAAS_ram_SEK+E72*IAAS_nvme_SEK+F72*IAAS_gpu_SEK -> 6950 | K72: =J63 -> Instanser | L72: =ROUNDUP(I72*H72,2) -> 0 | M72: =J72*C72*SW_win.ser.201X_SEK -> 0
B73: INSTANCE-glm.xlarge.2d | C73: 8 | D73: 32 | E73: 500 | F73: 2 | G73: =H73/720 -> 19.305556 | H73: =C73*IAAS_vcpu_SEK+D73*IAAS_ram_SEK+E73*IAAS_nvme_SEK+F73*IAAS_gpu_SEK -> 13900 | K73: Instanser | L73: =ROUNDUP(I73*H73,2) -> 0 | M73: =J73*C73*SW_win.ser.201X_SEK -> 0
B74: INSTANCE-glm.2xlarge.4d | C74: 16 | D74: 64 | E74: 1000 | F74: 4 | G74: =H74/720 -> 38.611111 | H74: =C74*IAAS_vcpu_SEK+D74*IAAS_ram_SEK+E74*IAAS_nvme_SEK+F74*IAAS_gpu_SEK -> 27800 | K74: =J65 -> Instanser | L74: =ROUNDUP(I74*H74,2) -> 0 | M74: =J74*C74*SW_win.ser.201X_SEK -> 0
B75: INSTANCE-glm.4xlarge.8d | C75: 32 | D75: 128 | E75: 1000 | F75: 6 | G75: =H75/720 -> 60.555556 | H75: =C75*IAAS_vcpu_SEK+D75*IAAS_ram_SEK+E75*IAAS_nvme_SEK+F75*IAAS_gpu_SEK -> 43600 | K75: Instanser | L75: =ROUNDUP(I75*H75,2) -> 0 | M75: =J75*C75*SW_win.ser.201X_SEK -> 0
B76: Totalt | I76: =SUM(I72:I75)&" st" -> 0 st | J76: =SUM(J72:J75)&" st" -> 0 st | L76: =SUM(L72:L75) -> 0 | M76: =SUM(M72:M75) -> 0
B79: "Bare Metal" compute
B80: Produkt ID | C80: CPU (p) core | D80: RAM (GB) | E80: NVME (GB) | G80: Per time | H80: Per måned | I80: Antall instanser | J80: Windows-lisenser | L80: Infrastruktur | M80: Lisenser
B81: INSTANCE-p1.2xlarge.16d | C81: 16 | D81: 128 | E81: 3800 | G81: =H81/720 -> 9.5 | H81: =INSTANCE_p1.2xlarge.16d_SEK -> 6840 | K81: Instanser | L81: =ROUNDUP(I81*H81,2) -> 0 | M81: =J81*C81*SW_win.ser.201X_SEK -> 0
B82: INSTANCE-p1.4xlarge.16d | C82: 32 | D82: 256 | E82: 3800 | G82: =H82/720 -> 19 | H82: =INSTANCE_p1.4xlarge.16d_SEK -> 13680 | K82: =K81 -> Instanser | L82: =ROUNDUP(I82*H82,2) -> 0 | M82: =J82*C82*SW_win.ser.201X_SEK -> 0
B83: INSTANCE-p1.8xlarge.32d | C83: 64 | D83: 512 | E83: 7600 | G83: =H83/720 -> 38 | H83: =INSTANCE_p1.8xlarge.32d_SEK -> 27360 | K83: Instanser | L83: =ROUNDUP(I83*H83,2) -> 0 | M83: =J83*C83*SW_win.ser.201X_SEK -> 0
B84: Totalt | I84: =SUM(I81:I83)&" st" -> 0 st | J84: =SUM(J81:J83)&" st" -> 0 st | L84: =SUM(L81:L83) -> 0 | M84: =SUM(M81:M83) -> 0
B87: Ekstra lagring
B88: Produkt ID | C88: Beskrivelse | E88: Per time | F88: Per GB/måned | I88: Ekstra GB | K88: Pris
B89: VOLUME-large | C89: HDD-backed 3-replica Ceph | E89: =F89/720 -> 0.0016666667 | F89: =VOLUME_large_SEK -> 1.2 | J89: GB | K89: =ROUNDUP(I89*F89,2) -> 0
B90: VOLUME-fast | C90: SSD-backed 3-replica Ceph | E90: =F90/720 -> 0.005 | F90: =VOLUME_fast_SEK -> 3.6 | J90: GB | K90: =ROUNDUP(I90*F90,2) -> 0
B91: Totalt | I91: =SUM(I89:I90)&" GB" -> 0 GB | K91: =SUM(K89:K90) -> 0
B95: Safespring Storage
B98: Objektlagring med standard S3.
B99: Prismodell basert på antall lagrede TB, se tabellen nedenfor.
B100: Instruksjoner: Fyll ut ønsket mengde i de fargede feltene.
B102: Produkt ID | C102: Antall TB | D102: Per TB/måned
B103: S3-storage | C103: 0 - 50 | D103: =S3_storage.50_SEK -> 350
B104: S3-storage | C104: 51 - 100 | D104: =S3_storage.100_SEK -> 270
B105: S3-storage | C105: 101 - 500 | D105: =S3_storage.500_SEK -> 200
B106: S3-storage | C106: 501 - 1000 | D106: =S3_storage.1000_SEK -> 185
B107: S3-storage | C107: 1001 - | D107: =S3_storage.quote_SEK -> Be om offert
B110: Produkt ID | F110: Per TB/måned | H110: Antall TB | M110: Pris
B111: S3-storage | F111: {=_xlfn.IFS(H111<51,D103,H111<101,D104,H111<501,D105,H111<1001,D106,H111>1000,D107)} -> 350 | I111: TB | M111: {=_xlfn.IFS(H111<1001,ROUNDUP(H111*F111,2),H111>1000,D107)} -> 0
B112: Totalt | M112: =SUM(M111) -> 0
B116: Safespring Backup
B119: Cloud backup-løsning for lokale servere eller skyservere basert på Spectrum Protect.
B120: Alle priser er oppgitt i NOK, eksklusiv mva.
B121: Instruksjoner: Fyll ut ønsket mengde i de fargede feltene.
B123: Produkt ID | C123: Fast månedlig pris | E123: Per time | F123: Per GB/måned | H123: Antal GB | J123: Deduplisering* | M123: Pris
B124: BAAS-on.demand ** | D124: N/A | E124: N/A | F124: =BAAS_on.demand_SEK -> 2.45 | I124: GB | J124: N/A | M124: =ROUNDUP(H124*F124,2) -> 0
B125: BAAS-small **** | D125: 5500 | E125: N/A | F125: =BAAS_small_SEK -> 1.75 | I125: GB | J125: 0.75 | M125: =IF(H125>0,IF(SUM($D$125+($F$125*((H125*(1-$J$125))-1000)))<=D125,$D$125,$D$125+($F$125*((H125*(1-$J$125))-1000))),0) -> 0
B126: BAAS-large *** | D126: 9500 | E126: N/A | F126: =BAAS_large_SEK -> 0.92 | I126: GB | J126: 0.75 | M126: =IF(H126>0,$D$126+($F$126*(H126*(1-$J$126))),0) -> 0
B127: Totalt | H127: =SUM(H124:H126)&" GB" -> 0 GB | M127: =SUM(M124:M126) -> 0
B129: * Dedup er en datareduksjon som er gjort i tjenesten. Avhengig av data varierer det normalt mellom 45% -90%
B130: ** Prisen er per beskyttet GB på klienten.
B131: *** Prisen er per lagret GB i tjenesten etter deduplisering og komprimering.
B132: **** Prisen er per lagret GB i tjenesten etter deduplisering og komprimering. 1000 GB er inkludert i den faste månedlige prisen.
B137: Nettverk og programvare
B140: Alle priser er oppgitt i NOK, eksklusiv mva.
B143: Nettverk
B144: Produkt ID | C144: Type | E144: Beskrivelse | L144: Pris per | M144: Per måned
B145: NET-publicv4 | C145: IPv4 | E145: Publik | L145: IP adresse | M145: =NET_publicv4_SEK -> 25
B146: NET-publicv6 | C146: IPv6 | E146: Publik | L146: N/A | M146: =NET_publicv6_SEK -> 0
B147: NET-ingress | C147: Datatrafikk | L147: GB | M147: =NET_ingress_SEK -> 0
B148: NET-egress | C148: Datatrafikk | E148: 1 TB / måned inkludert per prosjekt (gratis i akademisk sektor) | L148: GB | M148: =NET_egress_SEK -> 0
B149: NET-mgn.slb | C149: Managed SLB | L149: Instans | M149: =NET_mgn.slb_SEK -> 275
B150: NET-rdns | C150: Reverse DNS names | L150: N/A | M150: =NET_rdns_SEK -> 0
B151: NET-byoip | C151: Bring your own IP prefixes | L151: N/A | M151: =NET_byoip_SEK -> 0
B153: Programvare og lisenser
B154: Produkt ID | C154: Type | E154: Beskrivelse | L154: Pris per | M154: Per måned
B155: SW-win.ser.2016 | E155: Windows Server 2016 | L155: vCPU | M155: =SW_win.ser.201X_SEK -> 175
B156: SW-win.ser.2019 | E156: Windows Server 2019 | L156: vCPU | M156: =SW_win.ser.201X_SEK -> 175
...

Sheet SUNET SEK - priser 2020
B5: Priskalkylator 2020-07-02
B8: Kontakta Safespring | D8: Valuta
B9: Telefon: 08-55 10 73 56 | D9: SEK
B10: sales@safespring.se
B15: Safespring Compute
B18: Infrastruktur kan köras med kostnadsfri opensource-licens eller med Windows-licens.
B19: Alla priser är angivna i SEK, exklusive moms.
B20: Instruktioner: Fyll i önskad kvantitet i de färgade fälten.
B23: Instanser med central blocklagring
B24: Produkt ID | C24: Region | D24: vCPU | E24: RAM (GB) | F24: Disk (GB) | G24: Per timme | H24: Per månad | I24: Antal instanser | J24: Windows-licenser | K24: SQL-licenser | M24: Infrastruktur | N24: Licenser
B25: INSTANCE-b.tiny | C25: STO-1 | D25: 1 | E25: 1 | F25: 40 | G25: =H25/720 -> 17.95 | H25: =D25*IAAS_vcpu_sunet_b_m+E25*IAAS_ram_sunet_b_m+F25*IAAS_ssd_SUNET -> 12924 | L25: Instanser | M25: =ROUNDUP(I25*H25,2) -> 0 | N25: =J25*D25*SW_win.ser.201X_SEK+K25*D25*SW_ms.sql.ser_SEK -> 0
B26: INSTANCE-b.small | C26: STO-1 | D26: 1 | E26: 2 | F26: 40 | G26: =H26/720 -> 20.755556 | H26: =D26*IAAS_vcpu_sunet_b_m+E26*IAAS_ram_sunet_b_m+F26*IAAS_ssd_SUNET -> 14944 | L26: Instanser | M26: =ROUNDUP(I26*H26,2) -> 0 | N26: =J26*D26*SW_win.ser.201X_SEK+K26*D26*SW_ms.sql.ser_SEK -> 0
B27: INSTANCE-b.medium | C27: STO-1 | D27: 2 | E27: 4 | F27: 40 | G27: =H27/720 -> 41.511111 | H27: =D27*IAAS_vcpu_sunet_b_m+E27*IAAS_ram_sunet_b_m+F27*IAAS_ssd_SUNET -> 29888 | L27: Instanser | M27: =ROUNDUP(I27*H27,2) -> 0 | N27: =J27*D27*SW_win.ser.201X_SEK+K27*D27*SW_ms.sql.ser_SEK -> 0
B28: INSTANCE-b.large | C28: STO-1 | D28: 4 | E28: 8 | F28: 40 | G28: =H28/720 -> 83.022222 | H28: =D28*IAAS_vcpu_sunet_b_m+E28*IAAS_ram_sunet_b_m+F28*IAAS_ssd_SUNET -> 59776 | L28: Instanser | M28: =ROUNDUP(I28*H28,2) -> 0 | N28: =J28*D28*SW_win.ser.201X_SEK+K28*D28*SW_ms.sql.ser_SEK -> 0
B29: INSTANCE-b.xlarge | C29: STO-1 | D29: 8 | E29: 16 | F29: 40 | G29: =H29/720 -> 166.04444 | H29: =D29*IAAS_vcpu_sunet_b_m+E29*IAAS_ram_sunet_b_m+F29*IAAS_ssd_SUNET -> 119552 | L29: Instanser | M29: =ROUNDUP(I29*H29,2) -> 0 | N29: =J29*D29*SW_win.ser.201X_SEK+K29*D29*SW_ms.sql.ser_SEK -> 0
B30: INSTANCE-b.2xlarge | C30: STO-1 | D30: 16 | E30: 32 | F30: 40 | G30: =H30/720 -> 332.08889 | H30: =D30*IAAS_vcpu_sunet_b_m+E30*IAAS_ram_sunet_b_m+F30*IAAS_ssd_SUNET -> 239104 | L30: Instanser | M30: =ROUNDUP(I30*H30,2) -> 0 | N30: =J30*D30*SW_win.ser.201X_SEK+K30*D30*SW_ms.sql.ser_SEK -> 0
B31: INSTANCE-m.small | C31: STO-1 | D31: 1 | E31: 4 | F31: 40 | G31: =H31/720 -> 26.366667 | H31: =D31*IAAS_vcpu_sunet_b_m+E31*IAAS_ram_sunet_b_m+F31*IAAS_ssd_SUNET -> 18984 | L31: Instanser | M31: =ROUNDUP(I31*H31,2) -> 0 | N31: =J31*D31*SW_win.ser.201X_SEK+K31*D31*SW_ms.sql.ser_SEK -> 0
B32: INSTANCE-m.medium | C32: STO-1 | D32: 2 | E32: 8 | F32: 40 | G32: =H32/720 -> 52.733333 | H32: =D32*IAAS_vcpu_sunet_b_m+E32*IAAS_ram_sunet_b_m+F32*IAAS_ssd_SUNET -> 37968 | L32: Instanser | M32: =ROUNDUP(I32*H32,2) -> 0 | N32: =J32*D32*SW_win.ser.201X_SEK+K32*D32*SW_ms.sql.ser_SEK -> 0
B33: INSTANCE-m.large | C33: STO-1 | D33: 4 | E33: 16 | F33: 40 | G33: =H33/720 -> 105.46667 | H33: =D33*IAAS_vcpu_sunet_b_m+E33*IAAS_ram_sunet_b_m+F33*IAAS_ssd_SUNET -> 75936 | L33: Instanser | M33: =ROUNDUP(I33*H33,2) -> 0 | N33: =J33*D33*SW_win.ser.201X_SEK+K33*D33*SW_ms.sql.ser_SEK -> 0
B34: INSTANCE-m.xlarge | C34: STO-1 | D34: 8 | E34: 32 | F34: 40 | G34: =H34/720 -> 210.93333 | H34: =D34*IAAS_vcpu_sunet_b_m+E34*IAAS_ram_sunet_b_m+F34*IAAS_ssd_SUNET -> 151872 | L34: Instanser | M34: =ROUNDUP(I34*H34,2) -> 0 | N34: =J34*D34*SW_win.ser.201X_SEK+K34*D34*SW_ms.sql.ser_SEK -> 0
B35: INSTANCE-m.2xlarge | C35: STO-1 | D35: 16 | E35: 65 | F35: 40 | G35: =H35/720 -> 424.67222 | H35: =D35*IAAS_vcpu_sunet_b_m+E35*IAAS_ram_sunet_b_m+F35*IAAS_ssd_SUNET -> 305764 | L35: Instanser | M35: =ROUNDUP(I35*H35,2) -> 0 | N35: =J35*D35*SW_win.ser.201X_SEK+K35*D35*SW_ms.sql.ser_SEK -> 0
B36: Totalt | I36: =SUM(I25:I35)&" st" -> 0 st | J36: =SUM(J25:J35)&" st" -> 0 st | K36: =SUM(K25:K35)&" st" -> 0 st | M36: =SUM(M25:M35) -> 0 | N36: =SUM(N25:N35) -> 0
B39: Instanser med lokal lagring (NVMe-disk)
B40: Produkt ID | C40: Region | D40: vCPU | E40: RAM (GB) | F40: Disk (GB) | G40: Per timme | H40: Per månad | I40: Antal instanser | J40: Windows-licenser | K40: SQL-licenser | M40: Infrastruktur | N40: Licenser
B41: INSTANCE-lb.tiny | C41: STO-1 | D41: 1 | E41: 1 | F41: 10 | G41: =H41/720 -> 0.20138889 | H41: =D41*IAAS_vcpu_SUNET+E41*IAAS_ram_SUNET+F41*IAAS_nvme_SUNET -> 145 | L41: Instanser | M41: =ROUNDUP(I41*H41,2) -> 0 | N41: =J41*D41*SW_win.ser.201X_SEK+K41*D41*SW_ms.sql.ser_SEK -> 0
B42: INSTANCE-lb.large.1d | C42: STO-1 | D42: 4 | E42: 8 | F42: 250 | G42: =H42/720 -> 1.4027778 | H42: =D42*IAAS_vcpu_SUNET+E42*IAAS_ram_SUNET+F42*IAAS_nvme_SUNET -> 1010 | L42: Instanser | M42: =ROUNDUP(I42*H42,2) -> 0 | N42: =J42*D42*SW_win.ser.201X_SEK+K42*D42*SW_ms.sql.ser_SEK -> 0
B43: INSTANCE-lb.xlarge.1d | C43: STO-1 | D43: 8 | E43: 16 | F43: 250 | G43: =H43/720 -> 2.4583333 | H43: =D43*IAAS_vcpu_SUNET+E43*IAAS_ram_SUNET+F43*IAAS_nvme_SUNET -> 1770 | L43: Instanser | M43: =ROUNDUP(I43*H43,2) -> 0 | N43: =J43*D43*SW_win.ser.201X_SEK+K43*D43*SW_ms.sql.ser_SEK -> 0
B44: INSTANCE-lb.2xlarge.1d | C44: STO-1 | D44: 16 | E44: 32 | F44: 250 | G44: =H44/720 -> 4.5694444 | H44: =D44*IAAS_vcpu_SUNET+E44*IAAS_ram_SUNET+F44*IAAS_nvme_SUNET -> 3290 | L44: Instanser | M44: =ROUNDUP(I44*H44,2) -> 0 | N44: =J44*D44*SW_win.ser.201X_SEK+K44*D44*SW_ms.sql.ser_SEK -> 0
B45: INSTANCE-lb.2xlarge.2d | C45: STO-1 | D45: 16 | E45: 32 | F45: 500 | G45: =H45/720 -> 4.9166667 | H45: =D45*IAAS_vcpu_SUNET+E45*IAAS_ram_SUNET+F45*IAAS_nvme_SUNET -> 3540 | L45: Instanser | M45: =ROUNDUP(I45*H45,2) -> 0 | N45: =J45*D45*SW_win.ser.201X_SEK+K45*D45*SW_ms.sql.ser_SEK -> 0
B46: INSTANCE-lb.2xlarge.4d | C46: STO-1 | D46: 16 | E46: 32 | F46: 1000 | G46: =H46/720 -> 5.6111111 | H46: =D46*IAAS_vcpu_SUNET+E46*IAAS_ram_SUNET+F46*IAAS_nvme_SUNET -> 4040 | L46: Instanser | M46: =ROUNDUP(I46*H46,2) -> 0 | N46: =J46*D46*SW_win.ser.201X_SEK+K46*D46*SW_ms.sql.ser_SEK -> 0
B47: INSTANCE-lb.4xlarge.1d | C47: STO-1 | D47: 32 | E47: 65 | F47: 250 | G47: =H47/720 -> 8.8680556 | H47: =D47*IAAS_vcpu_SUNET+E47*IAAS_ram_SUNET+F47*IAAS_nvme_SUNET -> 6385 | L47: Instanser | M47: =ROUNDUP(I47*H47,2) -> 0 | N47: =J47*D47*SW_win.ser.201X_SEK+K47*D47*SW_ms.sql.ser_SEK -> 0
B48: INSTANCE-lb.4xlarge.2d | C48: STO-1 | D48: 32 | E48: 65 | F48: 500 | G48: =H48/720 -> 9.2152778 | H48: =D48*IAAS_vcpu_SUNET+E48*IAAS_ram_SUNET+F48*IAAS_nvme_SUNET -> 6635 | L48: Instanser | M48: =ROUNDUP(I48*H48,2) -> 0 | N48: =J48*D48*SW_win.ser.201X_SEK+K48*D48*SW_ms.sql.ser_SEK -> 0
B49: INSTANCE-lb.4xlarge.4d | C49: STO-1 | D49: 32 | E49: 65 | F49: 1000 | G49: =H49/720 -> 9.9097222 | H49: =D49*IAAS_vcpu_SUNET+E49*IAAS_ram_SUNET+F49*IAAS_nvme_SUNET -> 7135 | L49: Instanser | M49: =ROUNDUP(I49*H49,2) -> 0 | N49: =J49*D49*SW_win.ser.201X_SEK+K49*D49*SW_ms.sql.ser_SEK -> 0
B50: INSTANCE-lm.large.1d | C50: STO-1 | D50: 4 | E50: 16 | F50: 250 | G50: =H50/720 -> 2.0138889 | H50: =D50*IAAS_vcpu_SUNET+E50*IAAS_ram_SUNET+F50*IAAS_nvme_SUNET -> 1450 | L50: Instanser | M50: =ROUNDUP(I50*H50,2) -> 0 | N50: =J50*D50*SW_win.ser.201X_SEK+K50*D50*SW_ms.sql.ser_SEK -> 0
B51: INSTANCE-lm.xlarge.1d | C51: STO-1 | D51: 8 | E51: 32 | F51: 250 | G51: =H51/720 -> 3.6805556 | H51: =D51*IAAS_vcpu_SUNET+E51*IAAS_ram_SUNET+F51*IAAS_nvme_SUNET -> 2650 | L51: Instanser | M51: =ROUNDUP(I51*H51,2) -> 0 | N51: =J51*D51*SW_win.ser.201X_SEK+K51*D51*SW_ms.sql.ser_SEK -> 0
B52: INSTANCE-lm.xlarge.2d | C52: STO-1 | D52: 8 | E52: 32 | F52: 500 | G52: =H52/720 -> 4.0277778 | H52: =D52*IAAS_vcpu_SUNET+E52*IAAS_ram_SUNET+F52*IAAS_nvme_SUNET -> 2900 | L52: Instanser | M52: =ROUNDUP(I52*H52,2) -> 0 | N52: =J52*D52*SW_win.ser.201X_SEK+K52*D52*SW_ms.sql.ser_SEK -> 0
... B59: INSTANCE-lm.4xlarge.4d | C59: STO-1 | D59: 32 | E59: 131 | F59: 1000 | G59: =H59/720 -> 14.951389 | H59: =D59*IAAS_vcpu_SUNET+E59*IAAS_ram_SUNET+F59*IAAS_nvme_SUNET -> 10765 | L59: Instanser | M59: =ROUNDUP(I59*H59,2) -> 0 | N59: =J59*D59*SW_win.ser.201X_SEK+K59*D59*SW_ms.sql.ser_SEK -> 0
B60: Totalt | I60: =SUM(I41:I59)&" st" -> 0 st | J60: =SUM(J41:J59)&" st" -> 0 st | K60: =SUM(K41:K59)&" st" -> 0 st | M60: =SUM(M41:M59) -> 0 | N60: =SUM(N41:N59) -> 0
B63: SUNET Private Cloud
B64: Produkt ID | C64: Region | D64: CPU (p) core | E64: RAM (GB) | F64: Disk (GB) | G64: Per timme | H64: Per månad | I64: Antal instanser | J64: Windows-licenser | K64: SQL-licenser | M64: Infrastruktur | N64: Licenser
B65: lb.tiny | C65: STH-B | D65: 1 | E65: 1 | F65: 10 | G65: =H65/720 -> 0.1875 | H65: =D65*IAAS_vcpu_SUNET+E65*IAAS_ram_SUNET+F65*IAAS_ssd_SUNET -> 135 | L65: Instanser | M65: =ROUNDUP(I65*H65,2) -> 0 | N65: =J65*D65*SW_win.ser.201X_SEK+K65*D65*SW_ms.sql.ser_SEK -> 0
B66: lb.small | C66: STH-B | D66: 1 | E66: 2 | F66: 20 | G66: =H66/720 -> 0.26388889 | H66: =D66*IAAS_vcpu_SUNET+E66*IAAS_ram_SUNET+F66*IAAS_ssd_SUNET -> 190 | L66: Instanser | M66: =ROUNDUP(I66*H66,2) -> 0 | N66: =J66*D66*SW_win.ser.201X_SEK+K66*D66*SW_ms.sql.ser_SEK -> 0
B67: lb.medium.1d | C67: STH-B | D67: 2 | E67: 4 | F67: 250 | G67: =H67/720 -> 0.52777778 | H67: =D67*IAAS_vcpu_SUNET+E67*IAAS_ram_SUNET+F67*IAAS_ssd_SUNET -> 380 | L67: Instanser | M67: =ROUNDUP(I67*H67,2) -> 0 | N67: =J67*D67*SW_win.ser.201X_SEK+K67*D67*SW_ms.sql.ser_SEK -> 0
B68: lb.large.1d | C68: STH-B | D68: 4 | E68: 8 | F68: 250 | G68: =H68/720 -> 1.0555556 | H68: =D68*IAAS_vcpu_SUNET+E68*IAAS_ram_SUNET+F68*IAAS_ssd_SUNET -> 760 | L68: Instanser | M68: =ROUNDUP(I68*H68,2) -> 0 | N68: =J68*D68*SW_win.ser.201X_SEK+K68*D68*SW_ms.sql.ser_SEK -> 0
B69: lb.xlarge.1d | C69: STH-B | D69: 8 | E69: 16 | F69: 250 | G69: =H69/720 -> 2.1111111 | H69: =D69*IAAS_vcpu_SUNET+E69*IAAS_ram_SUNET+F69*IAAS_ssd_SUNET -> 1520 | L69: Instanser | M69: =ROUNDUP(I69*H69,2) -> 0 | N69: =J69*D69*SW_win.ser.201X_SEK+K69*D69*SW_ms.sql.ser_SEK -> 0
B70: lb.2xlarge.1d | C70: STH-B | D70: 16 | E70: 32 | F70: 250 | G70: =H70/720 -> 4.2222222 | H70: =D70*IAAS_vcpu_SUNET+E70*IAAS_ram_SUNET+F70*IAAS_ssd_SUNET -> 3040 | L70: Instanser | M70: =ROUNDUP(I70*H70,2) -> 0 | N70: =J70*D70*SW_win.ser.201X_SEK+K70*D70*SW_ms.sql.ser_SEK -> 0
B71: lb.2xlarge.2d | C71: STH-B | D71: 16 | E71: 32 | F71: 500 | G71: =H71/720 -> 4.2222222 | H71: =D71*IAAS_vcpu_SUNET+E71*IAAS_ram_SUNET+F71*IAAS_ssd_SUNET -> 3040 | L71: Instanser | M71: =ROUNDUP(I71*H71,2) -> 0 | N71: =J71*D71*SW_win.ser.201X_SEK+K71*D71*SW_ms.sql.ser_SEK -> 0
B72: lb.2xlarge.4d | C72: STH-B | D72: 16 | E72: 32 | F72: 1000 | G72: =H72/720 -> 4.2222222 | H72: =D72*IAAS_vcpu_SUNET+E72*IAAS_ram_SUNET+F72*IAAS_ssd_SUNET -> 3040 | L72: Instanser | M72: =ROUNDUP(I72*H72,2) -> 0 | N72: =J72*D72*SW_win.ser.201X_SEK+K72*D72*SW_ms.sql.ser_SEK -> 0
B73: lb.4xlarge.1d | C73: STH-B | D73: 32 | E73: 65 | F73: 250 | G73: =H73/720 -> 8.5208333 | H73: =D73*IAAS_vcpu_SUNET+E73*IAAS_ram_SUNET+F73*IAAS_ssd_SUNET -> 6135 | L73: Instanser | M73: =ROUNDUP(I73*H73,2) -> 0 | N73: =J73*D73*SW_win.ser.201X_SEK+K73*D73*SW_ms.sql.ser_SEK -> 0
B74: lb.4xlarge.2d | C74: STH-B | D74: 32 | E74: 65 | F74: 500 | G74: =H74/720 -> 8.5208333 | H74: =D74*IAAS_vcpu_SUNET+E74*IAAS_ram_SUNET+F74*IAAS_ssd_SUNET -> 6135 | L74: Instanser | M74: =ROUNDUP(I74*H74,2) -> 0 | N74: =J74*D74*SW_win.ser.201X_SEK+K74*D74*SW_ms.sql.ser_SEK -> 0
B75: lb.4xlarge.4d | C75: STH-B | D75: 32 | E75: 65 | F75: 1000 | G75: =H75/720 -> 8.5208333 | H75: =D75*IAAS_vcpu_SUNET+E75*IAAS_ram_SUNET+F75*IAAS_ssd_SUNET -> 6135 | L75: Instanser | M75: =ROUNDUP(I75*H75,2) -> 0 | N75: =J75*D75*SW_win.ser.201X_SEK+K75*D75*SW_ms.sql.ser_SEK -> 0
B76: lm.small | C76: STH-B | D76: 1 | E76: 4 | F76: 20 | G76: =H76/720 -> 0.41666667 | H76: =D76*IAAS_vcpu_SUNET+E76*IAAS_ram_SUNET+F76*IAAS_ssd_SUNET -> 300 | L76: Instanser | M76: =ROUNDUP(I76*H76,2) -> 0 | N76: =J76*D76*SW_win.ser.201X_SEK+K76*D76*SW_ms.sql.ser_SEK -> 0
... B85: lm.4xlarge.4d | C85: STH-B | D85: 32 | E85: 131 | F85: 1000 | G85: =H85/720 -> 13.5625 | H85: =D85*IAAS_vcpu_SUNET+E85*IAAS_ram_SUNET+F85*IAAS_ssd_SUNET -> 9765 | L85: Instanser | M85: =ROUNDUP(I85*H85,2) -> 0 | N85: =J85*D85*SW_win.ser.201X_SEK+K85*D85*SW_ms.sql.ser_SEK -> 0
B86: Totalt | I86: =SUM(I65:I85)&" st" -> 0 st | J86: =SUM(J65:J85)&" st" -> 0 st | K86: =SUM(K65:K85)&" st" -> 0 st | M86: =SUM(M65:M85) -> 0 | N86: =SUM(N65:N85) -> 0
B89: Bare Metal compute
B90: Produkt ID | C90: CPU (p) core | D90: RAM (GB) | E90: NVME (GB) | G90: Per timme | H90: Per månad | I90: Antal instanser | J90: Windows-licenser | K90: SQL-licenser | M90: Infrastruktur | N90: Licenser
B91: INSTANCE-p1.2xlarge.16d | C91: 16 | D91: 128 | E91: 3800 | G91: =H91/720 -> 9.5 | H91: =INSTANCE_p1.2xlarge.16d_SEK -> 6840 | I91: 0 | J91: 0 | K91: 0 | L91: Instanser | M91: =ROUNDUP(I91*H91,2) -> 0 | N91: =J91*C91*SW_win.ser.201X_SEK+K91*C91*SW_ms.sql.ser_SEK -> 0
B92: INSTANCE-p1.4xlarge.16d | C92: 32 | D92: 256 | E92: 3800 | G92: =H92/720 -> 19 | H92: =INSTANCE_p1.4xlarge.16d_SEK -> 13680 | I92: 0 | J92: 0 | K92: 0 | L92: =L91 -> Instanser | M92: =ROUNDUP(I92*H92,2) -> 0 | N92: =J92*C92*SW_win.ser.201X_SEK+K92*C92*SW_ms.sql.ser_SEK -> 0
B93: INSTANCE-p1.8xlarge.32d | C93: 64 | D93: 512 | E93: 7600 | G93: =H93/720 -> 38 | H93: =INSTANCE_p1.8xlarge.32d_SEK -> 27360 | I93: 0 | J93: 0 | K93: 0 | L93: Instanser | M93: =ROUNDUP(I93*H93,2) -> 0 | N93: =J93*C93*SW_win.ser.201X_SEK+K93*C93*SW_ms.sql.ser_SEK -> 0
B94: Totalt | I94: =SUM(I91:I93)&" st" -> 0 st | J94: =SUM(J91:J93)&" st" -> 0 st | K94: =SUM(K91:K93)&" st" -> 0 st | M94: =SUM(M91:M93) -> 0 | N94: =SUM(N91:N93) -> 0
B97: Extra lagring
B98: Produkt ID | C98: Beskrivning | E98: Per timme | F98: Per GB/månad | J98: Extra GB
B99: VOLUME-large | C99: SSD-backed 3-replica Ceph | E99: =F99/720 -> 0.0016666667 | F99: =VOLUME_large_SEK -> 1.2 | K99: GB | N99: =ROUNDUP(J99*F99,2) -> 0
B100: VOLUME-fast | C100: HDD-backed 3-replica Ceph | E100: =F100/720 -> 0.005 | F100: =VOLUME_fast_SEK -> 3.6 | J100: 0 | K100: GB | N100: =ROUNDUP(J100*F100,2) -> 0
B101: Totalt | J101: =SUM(J99:J100)&" GB" -> 0 GB | N101: =SUM(N99:N100) -> 0
B105: SUNET Lagring i privat molntjänst
B108: Objektlagring med standarden S3.
B109: Prismodell baserat på antal lagrade GB, se tabellen nedan.
B110: Instruktioner: Fyll i önskad kvantitet i de färgade fälten.
B112: Produkt ID | C112: Antal TB | D112: Per GB /månad
B113: S3-storage | C113: <300 | D113: =S3_storage.50_SUNET -> 0.35
B114: S3-storage | C114: >=300 | D114: =S3_storage.100_SUNET -> 0.19
B115: S3-storage | C115: >=1000 | D115: =S3_storage.500_SUNET -> 0.1
B116: S3-storage | C116: >=2000 | D116: =S3_storage.1000_SUNET -> 0.06
B117: S3-storage | C117: 1001 - | D117: =S3_storage.quote_SUNET -> Be om offert
B120: Produkt ID | E120: Per timme | F120: Per GB/månad | H120: Antal TB | K120: Minsta åtagande | N120: Storage
B121: S3-storage | E121: =F121/720 -> 0.00048611111 | F121: {=_xlfn.IFS(H121<=299,D113,H121<1000,D114,H121<2000,D115,H121>=2000,D116)} -> 0.35 | H121: 0 | I121: TB | K121: {=_xlfn.IFS(H121<=299,"6 månader",H121<1000,"12 månader",H121<2000,"12 månader",H121>=2000,"36 månader")} -> 6 månader | M121: =ROUNDUP((H121*1000)*F121,2) -> 0
B122: Totalt | M122: =SUM(M121) -> 0
B126: Safespring Backup
B129: Cloud backup solution for on-prem or cloud servers based on Spectrum Protect.
B130: Alla priser angivna i SEK, exklusive moms.
B131: Instruktioner: Fyll i önskad kvantitet i de färgade fälten.
B133: Produkt ID | C133: Fast månadspris | E133: Per timme | F133: Per GB/månad | H133: Antal GB | J133: Deduplicering* | N133: Pris
B134: BAAS-on.demand ** | D134: N/A | E134: N/A | F134: =BAAS_on.demand_SEK -> 2.45 | H134: 0 | I134: GB | J134: N/A | N134: =ROUNDUP(H134*F134,2) -> 0
B135: BAAS-small **** | D135: 5500 | E135: N/A | F135: =BAAS_small_SEK -> 1.75 | H135: 0 | I135: GB | J135: 0.75 | N135: =IF(H135>0,IF(SUM($D$135+($F$135*((H135*(1-$J$135))-1000)))<=D135,$D$135,$D$135+($F$135*((H135*(1-$J$135))-1000))),0) -> 0
B136: BAAS-large *** | D136: 9500 | E136: N/A | F136: =BAAS_large_SEK -> 0.92 | H136: 0 | I136: GB | J136: 0.75 | N136: =IF(H136>0,$D$136+($F$136*(H136*(1-$J$136))),0) -> 0
B137: Totalt | H137: =SUM(H134:H136)&" GB" -> 0 GB | N137: =SUM(N134:N136) -> 0
B139: * Dedup är en datareduktion som görs i tjänsten. Beroende på data varierar det normalt mellan 45%-90%
B140: ** Priset är per skyddad GB på klienten.
B141: *** Priset är per lagrad GB i tjänsten efter deduplicering och komprimering.
B142: **** Priset är per lagrad GB i tjänsten efter deduplicering och komprimering. Det ingår 1000GB i det fasta månadspriset.
B150: Månadskostnad
B153: Alla priser angivna i SEK, exklusive moms.
B155: Kontakta Safespring för fullständig offert
B156: Telefon: 08-55 10 73 56
B157: sales@safespring.se
B159: Produkt | M159: Månadskostnad
B160: Safespring Compute | M160: =M86+M94+M60+M36+N101 -> 0
B161: Safespring Storage | M161: =M122 -> 0
B162: Safespring Backup | M162: =N137 -> 0
...

Sheet DKK - Safespring-tjenester 2025
B5: Prisberegner 2026-05-25
B8: Kontakt Safespring | D8: Valuta
B9: Telefon: +46 8-55 10 73 56
B10: hello@safespring.com
D11: Fakturaen vil være i DKK, hvor den gennemsnitlige valutakurs, baseret på valutakurserne fra ECB, pr. måned bruges til at beregne priserne.
B15: Safespring Kubernetes Engine
B18: Alle priser er i EUR, eksklusive moms.
B19: Vejledning: Udfyld det ønskede antal i de farvede felter.
B22: Kontrolplan
B23: Det første kontrolplan er administreret, men derefter er det muligt at tilføje ikke-administrerede kontrolplaner.
B24: Produkt ID | G24: Per time | H24: Per 30 dage | I24: Antal | K24: Infrastruktur
B25: Managed Control plane | G25: =H25/720 -> 0.63972222 | H25: ='EUR - Safespring services 2025'!H25 -> 460.6 | K25: =ROUNDUP(I25*H25,2) -> 0
B26: Unmanaged Control plane | G26: =H26/720 -> 0 | H26: 0 | K26: =ROUNDUP(I26*H26,2) -> 0
B27: I alt | I27: =SUM(I14:I26)&" stk." -> 0 stk. | K27: =SUM(K14:K26) -> 0
B30: Safespring Compute | IaaS
B33: Infrastruktur kan køre med en Open Source-licens eller med en Windows-licens.
B34: Alle priser er i EUR, eksklusive moms. Fakturaen vil være i DKK, hvor den gennemsnitlige valutakurs, baseret på valutakurserne fra ECB, pr. måned bruges til at beregne priserne.
B35: Vejledning: Udfyld det ønskede antal i de farvede felter.
B38: Flavors med lokal NVMe-disk
B39: Central bloklagring kan købes til instanserne. Se "Central bloklagring" i prislisten.
B40: Produkt ID | C40: vCPU | D40: RAM (GB) | E40: Lokal disk (GB) | G40: Per time | H40: Per 30 dage | I40: Antal | K40: Infrastruktur
B41: FLAVOR-l2. c2 r4. 100 | C41: 2 | D41: 4 | E41: 100 | G41: =H41/720 -> 0.062666667 | H41: =C41*IAAS_vcpu_EUR+D41*IAAS_ram_EUR+E41*IAAS_nvme_EUR -> 45.12 | K41: =ROUNDUP(I41*H41,2) -> 0
B42: FLAVOR-l2. c2 r4. 500 | C42: 2 | D42: 4 | E42: 500 | G42: =H42/720 -> 0.11488889 | H42: =C42*IAAS_vcpu_EUR+D42*IAAS_ram_EUR+E42*IAAS_nvme_EUR -> 82.72 | K42: =ROUNDUP(I42*H42,2) -> 0
B43: FLAVOR-l2. c2 r4. 1000 | C43: 2 | D43: 4 | E43: 1000 | G43: =H43/720 -> 0.18016667 | H43: =C43*IAAS_vcpu_EUR+D43*IAAS_ram_EUR+E43*IAAS_nvme_EUR -> 129.72 | K43: =ROUNDUP(I43*H43,2) -> 0
B44: FLAVOR-l2. c4 r8. 100 | C44: 4 | D44: 8 | E44: 100 | G44: =H44/720 -> 0.11227778 | H44: =C44*IAAS_vcpu_EUR+D44*IAAS_ram_EUR+E44*IAAS_nvme_EUR -> 80.84 | K44: =ROUNDUP(I44*H44,2) -> 0
B45: FLAVOR-l2. c4 r8. 500 | C45: 4 | D45: 8 | E45: 500 | G45: =H45/720 -> 0.1645 | H45: =C45*IAAS_vcpu_EUR+D45*IAAS_ram_EUR+E45*IAAS_nvme_EUR -> 118.44 | K45: =ROUNDUP(I45*H45,2) -> 0
B46: FLAVOR-l2. c4 r8. 1000 | C46: 4 | D46: 8 | E46: 1000 | G46: =H46/720 -> 0.22977778 | H46: =C46*IAAS_vcpu_EUR+D46*IAAS_ram_EUR+E46*IAAS_nvme_EUR -> 165.44 | K46: =ROUNDUP(I46*H46,2) -> 0
B47: FLAVOR-l2. c8 r16. 100 | C47: 8 | D47: 16 | E47: 100 | G47: =H47/720 -> 0.2115 | H47: =C47*IAAS_vcpu_EUR+D47*IAAS_ram_EUR+E47*IAAS_nvme_EUR -> 152.28 | K47: =ROUNDUP(I47*H47,2) -> 0
B48: FLAVOR-l2. c8 r16. 500 | C48: 8 | D48: 16 | E48: 500 | G48: =H48/720 -> 0.26372222 | H48: =C48*IAAS_vcpu_EUR+D48*IAAS_ram_EUR+E48*IAAS_nvme_EUR -> 189.88 | K48: =ROUNDUP(I48*H48,2) -> 0
B49: FLAVOR-l2. c8 r16. 1000 | C49: 8 | D49: 16 | E49: 1000 | G49: =H49/720 -> 0.329 | H49: =C49*IAAS_vcpu_EUR+D49*IAAS_ram_EUR+E49*IAAS_nvme_EUR -> 236.88 | K49: =ROUNDUP(I49*H49,2) -> 0
B50: FLAVOR-l2. c16 r32. 100 | C50: 16 | D50: 32 | E50: 100 | G50: =H50/720 -> 0.40994444 | H50: =C50*IAAS_vcpu_EUR+D50*IAAS_ram_EUR+E50*IAAS_nvme_EUR -> 295.16 | K50: =ROUNDUP(I50*H50,2) -> 0
B51: FLAVOR-l2. c16 r32. 500 | C51: 16 | D51: 32 | E51: 500 | G51: =H51/720 -> 0.46216667 | H51: =C51*IAAS_vcpu_EUR+D51*IAAS_ram_EUR+E51*IAAS_nvme_EUR -> 332.76 | K51: =ROUNDUP(I51*H51,2) -> 0
B52: FLAVOR-l2. c16 r32. 1000 | C52: 16 | D52: 32 | E52: 1000 | G52: =H52/720 -> 0.52744444 | H52: =C52*IAAS_vcpu_EUR+D52*IAAS_ram_EUR+E52*IAAS_nvme_EUR -> 379.76 | K52: =ROUNDUP(I52*H52,2) -> 0
... B54: FLAVOR-l2. c32 r64. 1000 | C54: 32 | D54: 64 | E54: 1000 | G54: =H54/720 -> 0.92433333 | H54: =C54*IAAS_vcpu_EUR+D54*IAAS_ram_EUR+E54*IAAS_nvme_EUR -> 665.52 | K54: =ROUNDUP(I54*H54,2) -> 0
B55: Total | C55: {=SUM(C41:C54*I41:I54)} -> 0 | D55: {=SUM(D41:D54*I41:I54)&" GB"} -> 0 GB | E55: {=SUM(E41:E54*I41:I54)&" GB"} -> 0 GB | I55: =SUM(I41:I54) -> 0 | K55: =SUM(K41:K54) -> 0
B59: Flavors uden lokal disk
B60: Central bloklagring kan købes til instanserne. Se "Central bloklagring" i prislisten.
B61: Produkt ID | C61: vCPU | D61: RAM (GB) | E61: Lokal disk (GB) | G61: Per time | H61: Per 30 dage | I61: Antal | K61: Infrastruktur
B62: FLAVOR-b2. c1 r2 | C62: 1 | D62: 2 | E62: 0 | G62: =H62/720 -> 0.024805556 | H62: =C62*IAAS_vcpu_EUR+D62*IAAS_ram_EUR+E62*IAAS_ssd_EUR -> 17.86 | K62: =ROUNDUP(I62*H62,2) -> 0
B63: FLAVOR-b2. c1 r4 | C63: 1 | D63: 4 | E63: 0 | G63: =H63/720 -> 0.039166667 | H63: =C63*IAAS_vcpu_EUR+D63*IAAS_ram_EUR+E63*IAAS_ssd_EUR -> 28.2 | K63: =ROUNDUP(I63*H63,2) -> 0
B64: FLAVOR-b2. c2 r4 | C64: 2 | D64: 4 | E64: 0 | G64: =H64/720 -> 0.049611111 | H64: =C64*IAAS_vcpu_EUR+D64*IAAS_ram_EUR+E64*IAAS_ssd_EUR -> 35.72 | K64: =ROUNDUP(I64*H64,2) -> 0
B65: FLAVOR-b2. c2 r8 | C65: 2 | D65: 8 | E65: 0 | G65: =H65/720 -> 0.078333333 | H65: =C65*IAAS_vcpu_EUR+D65*IAAS_ram_EUR+E65*IAAS_ssd_EUR -> 56.4 | K65: =ROUNDUP(I65*H65,2) -> 0
B66: FLAVOR-b2 .c4 r8 | C66: 4 | D66: 8 | E66: 0 | G66: =H66/720 -> 0.099222222 | H66: =C66*IAAS_vcpu_EUR+D66*IAAS_ram_EUR+E66*IAAS_ssd_EUR -> 71.44 | K66: =ROUNDUP(I66*H66,2) -> 0
B67: FLAVOR-b2. c4 r16 | C67: 4 | D67: 16 | E67: 0 | G67: =H67/720 -> 0.15666667 | H67: =C67*IAAS_vcpu_EUR+D67*IAAS_ram_EUR+E67*IAAS_ssd_EUR -> 112.8 | K67: =ROUNDUP(I67*H67,2) -> 0
B68: FLAVOR-b2. c8 r16 | C68: 8 | D68: 16 | E68: 0 | G68: =H68/720 -> 0.19844444 | H68: =C68*IAAS_vcpu_EUR+D68*IAAS_ram_EUR+E68*IAAS_ssd_EUR -> 142.88 | K68: =ROUNDUP(I68*H68,2) -> 0
B69: FLAVOR-b2. c8 r32 | C69: 8 | D69: 32 | E69: 0 | G69: =H69/720 -> 0.31333333 | H69: =C69*IAAS_vcpu_EUR+D69*IAAS_ram_EUR+E69*IAAS_ssd_EUR -> 225.6 | K69: =ROUNDUP(I69*H69,2) -> 0
B70: FLAVOR-b2. c16 r32 | C70: 16 | D70: 32 | E70: 0 | G70: =H70/720 -> 0.39688889 | H70: =C70*IAAS_vcpu_EUR+D70*IAAS_ram_EUR+E70*IAAS_ssd_EUR -> 285.76 | K70: =ROUNDUP(I70*H70,2) -> 0
B71: FLAVOR-b2. c16 r64 | C71: 16 | D71: 64 | E71: 0 | G71: =H71/720 -> 0.62666667 | H71: =C71*IAAS_vcpu_EUR+D71*IAAS_ram_EUR+E71*IAAS_ssd_EUR -> 451.2 | K71: =ROUNDUP(I71*H71,2) -> 0
B72: Total | C72: {=SUM(C62:C71*I62:I71)} -> 0 | D72: {=SUM(D62:D71*I62:I71)} -> 0 | E72: N/A | I72: =SUM(I62:I71) -> 0 | K72: =SUM(K62:K71) -> 0
B76: Flavors med GPU
B77: Central bloklagring kan købes til instanserne. Se "Central bloklagring" i prislisten.
B78: Produkt ID | C78: vCPU | D78: RAM (GB) | E78: Lokal disk (GB) | F78: Nvidia | G78: Per time | H78: Per 30 dage | I78: Antal instanser | K78: Infrastruktur
B79: FLAVOR-l2.c4r16.125.gA2 | C79: 4 | D79: 16 | E79: 125 | F79: A2 | G79: =H79/720 -> 0.43670833 | H79: =C79*IAAS_vcpu_EUR+D79*IAAS_ram_EUR+E79*IAAS_nvme_EUR+IAAS_GPU_A2_EUR -> 314.43 | K79: =ROUNDUP(I79*H79,2) -> 0
B80: FLAVOR-l2.c8r32.250.gA2 | C80: 8 | D80: 32 | E80: 250 | F80: A2 | G80: =H80/720 -> 0.60969444 | H80: =C80*IAAS_vcpu_EUR+D80*IAAS_ram_EUR+E80*IAAS_nvme_EUR+IAAS_GPU_A2_EUR -> 438.98 | K80: =ROUNDUP(I80*H80,2) -> 0
B81: FLAVOR-b2.c4r8.gA2 | C81: 4 | D81: 8 | E81: 0 | F81: A2 | G81: =H81/720 -> 0.36294444 | H81: =C81*IAAS_vcpu_EUR+D81*IAAS_ram_EUR+E81*IAAS_nvme_EUR+IAAS_GPU_A2_EUR -> 261.32 | K81: =ROUNDUP(I81*H81,2) -> 0
B82: FLAVOR-b2.c8r16.gA2 | C82: 8 | D82: 16 | E82: 0 | F82: A2 | G82: =H82/720 -> 0.46216667 | H82: =C82*IAAS_vcpu_EUR+D82*IAAS_ram_EUR+E82*IAAS_nvme_EUR+IAAS_GPU_A2_EUR -> 332.76 | K82: =ROUNDUP(I82*H82,2) -> 0
B83: FLAVOR-b2.c32.r192.gH100 | C83: 32 | D83: 192 | E83: 0 | F83: H100 | G83: =H83/720 -> 3.1364667 | H83: =C83*IAAS_vcpu_EUR+D83*IAAS_ram_EUR+E83*IAAS_nvme_EUR+IAAS_GPU_H100_EUR -> 2258.256 | K83: =ROUNDUP(I83*H83,2) -> 0
B84: I alt | C84: =SUMPRODUCT(C79:C83,I79:I83)&" stk." -> 0 stk. | D84: =SUMPRODUCT(D79:D83,I79:I83)&" GB" -> 0 GB | E84: =SUMPRODUCT(E79:E83,I79:I83)&" GB" -> 0 GB | I84: =SUM(I79:I83)&" stk." -> 0 stk. | K84: =SUM(K79:K83) -> 0
B86: Central bloklagring
B87: Central bloklagring giver tre kopier af data fordelt i en robust CEPH-klynge.
B88: Produkt ID | C88: Beskrivelse | G88: Per time | H88: Per 30 dage | I88: Antal (GB) | K88: Lagring
B89: VOLUME-large | C89: HDD-backed 3-replica Ceph | G89: =H89/720 -> 0.00015666667 | H89: =VOLUME_large_EUR -> 0.1128 | K89: =ROUNDUP(I89*H89,2) -> 0
B90: VOLUME-fast | C90: SSD-backed 3-replica Ceph | G90: =H90/720 -> 0.00047 | H90: =VOLUME_fast_EUR -> 0.3384 | K90: =ROUNDUP(I90*H90,2) -> 0
B91: VOLUME-snapshot | C91: Snapshot of image | G91: =H91/720 -> 0.00015666667 | H91: =VOLUME_large_EUR -> 0.1128 | K91: =ROUNDUP(I91*H91,2) -> 0
B92: Total | I92: =SUM(I89:I91)&" GB" -> 0 GB | K92: =SUM(K89:K91) -> 0
B95: Safespring Storage | S3
B98: Kontakt os for rabatter på større lagermængder. Prismodellen er baseret på antallet af lagrede TB pr. måned.
B99: Alle priser er i EUR, eksklusive moms. Fakturaen vil være i DKK, hvor den gennemsnitlige valutakurs, baseret på valutakurserne fra ECB, pr. måned bruges til at beregne priserne.
B100: Vejledning: Udfyld det ønskede antal i de farvede felter.
B102: Produkt ID | G102: Per TB i 30 dage | I102: Antal (TB) | K102: Lagring
B103: S3-archive | C103: Tilpasset større lagringsmængder over længere tid. | G103: =S3_archive.50_EUR -> 32.9 | K103: =I103*G103 -> 0
B104: S3-storage | C104: Tilpasset applikationer, der aktivt bruger S3-protokollen. | G104: =S3_storage50_EUR -> 47 | K104: =I104*G104 -> 0
B105: Total | K105: =SUM(K103:K104) -> 0
B109: Safespring Backup | SP
B112: Cloud backup-løsning for lokale servere eller cloud-servere baseret på Spectrum Protect (TSM).
B113: Alle priser er i EUR, eksklusive moms. Fakturaen vil være i DKK, hvor den gennemsnitlige valutakurs, baseret på valutakurserne fra ECB, pr. måned bruges til at beregne priserne.
B114: Vejledning: Udfyld det ønskede antal i de farvede felter.
B116: Produkt ID | E116: Fast månedlig pris | G116: Per GB i 30 dage | I116: Antal (GB) | J116: Deduplicering 1 | K116: Backup
B117: BAAS-on.demand 2 | E117: N/A | G117: =BAAS_on.demand_EUR -> 0.2303 | J117: N/A | K117: =ROUNDUP(I117*G117,2) -> 0
B118: BAAS-small 3 | E118: =BAAS_small.fee_EUR -> 517 | G118: =BAAS_small_EUR -> 0.1645 | J118: 0.75 | K118: =IF(I118>0,$E$118+$G$118*MAX(0,I118*(1-$J$118)-1000),0) -> 0
B119: BAAS-large 4 | E119: =BAAS_large.fee_EUR -> 893 | G119: =BAAS_large_EUR -> 0.08648 | J119: 0.75 | K119: =IF(I119>0,$E$119+($G$119*(I119*(1-$J$119))),0) -> 0
B120: Total | I120: =SUM(I117:I119)&" GB" -> 0 GB | K120: =SUM(K117:K119) -> 0
B124: Netværk og software
B127: Alle priser er i EUR, eksklusive moms. Fakturaen vil være i DKK, hvor den gennemsnitlige valutakurs, baseret på valutakurserne fra ECB, pr. måned bruges til at beregne priserne.
B129: Netværk
B130: Safespring tilbyder flere netværkstjenester.
B131: Produkt ID | C131: Type | E131: Beskrivelse | J131: Fakturering pr. | K131: Pr. måned
B132: NET-publicv4 | C132: IPv4 | E132: Offentlig | J132: IP-adresse | K132: =NET_publicv4_EUR -> 2.35
B133: NET-publicv6 | C133: IPv6 | E133: Offentlig | J133: N/A | K133: =NET_publicv6_EUR -> 0
B134: NET-ingress | C134: Dataoverførsel | J134: GB | K134: =NET_ingress_EUR -> 0
B135: NET-egress | C135: Dataoverførsel | J135: GB | K135: =NET_egress_EUR -> 0
B136: NET-mgn.slb | C136: Managed SLB (ElasticIP) | E136: Load balancer, der kræver deres egne instanser | J136: Instans | K136: Bed om tilbud
B137: NET-rdns | C137: Reverse DNS names | J137: N/A | K137: =NET_rdns_EUR -> 0
B138: NET-byoip | C138: Bring your own IP prefixes | J138: N/A | K138: 0
B142: Software og licenser
B143: Safespring tilbyder flere software og licenser.
B144: Produkt ID | E144: Beskrivelse | J144: Fakturering pr. | K144: Pr. måned
B145: SW-win.ser.2022 | E145: Microsoft Windows Server | J145: vCPU | K145: =SW_win.ser.201X_EUR -> 16.45
B146: SW-ms.sql.ser | E146: Microsoft SQL Server Standard | J146: vCPU | K146: =SW_ms.sql.ser_EUR -> 115.526
B147: SW-ms.sql.ser.ent | E147: Microsoft SQL Server Enterprise | J147: vCPU | K147: =SW_ms.sql.ser.ent_EUR -> 448.004
...

Sheet Data
B2: Safespring Compute | D2: Prissättning | E2: SEK/NOK | F2: EUR | G2: SUNET med påslag | I2: Currency Factor
B3: IAAS-ram | D3: 55 | E3: =D3*SEK -> 55 | F3: =D3*EUR -> 5.17 | G3: =(D3*(1+Safespring.price.increase))*(1+sunet.price.increase) -> 55 | I3: SEK | K3: 1
B4: IAAS-ssd | D4: 3.6 | E4: =D4*SEK -> 3.6 | F4: =D4*EUR -> 0.3384 | G4: =(D4*(1+Safespring.price.increase))*(1+sunet.price.increase) -> 3.6 | I4: EUR | K4: 0.094 | L4: uppdaterat 2026-02-27
B5: IAAS-vcpu | D5: 80 | E5: =D5*SEK -> 80 | F5: =D5*EUR -> 7.52 | G5: =(D5*(1+Safespring.price.increase))*(1+sunet.price.increase) -> 80 | I5: NOK | K5: 1
B6: IAAS-nvme | D6: 1 | E6: =D6*SEK -> 1 | F6: =D6*EUR -> 0.094 | G6: =(D6*(1+Safespring.price.increase))*(1+sunet.price.increase) -> 1
B7: IAAS-gpu | D7: 5500 | E7: =D7*SEK -> 5500 | F7: =D7*EUR -> 517 | G7: =(D7*(1+Safespring.price.increase))*(1+sunet.price.increase) -> 5500
B8: IAAS-pcpu (beräknad) | D8: 2.66 | E8: =D8*IAAS_vcpu_SEK*SEK -> 212.8 | F8: =D8*IAAS_vcpu_SEK*EUR -> 20.0032 | G8: =(D8*(1+Safespring.price.increase))*(1+sunet.price.increase) -> 2.66 | I8: Typ | J8: Antal | K8: Pris
B9: IAAS-GPU-A2 | D9: 2020 | E9: =D9*SEK -> 2020 | F9: =D9*EUR -> 189.88 | G9: =(D9*(1+Safespring.price.increase))*(1+sunet.price.increase) -> 2020 | I9: vCPU | K9: =J9*IAAS_vcpu_SEK -> 0
B10: IAAS-GPU-H100 | D10: 10904 | E10: =D10*SEK -> 10904 | F10: =D10*EUR -> 1024.976 | G10: =(D10*(1+Safespring.price.increase))*(1+sunet.price.increase) -> 10904 | I10: RAM | K10: =J10*IAAS_ram_SEK -> 0
E11: =D11*SEK -> 0 | F11: =D11*EUR -> 0 | G11: =(D11*(1+Safespring.price.increase))*(1+sunet.price.increase) -> 0 | I11: Totalt | K11: =SUM(K9:K10) -> 0
B13: Bare metal compute | D13: Prissättning | E13: SEK | F13: EUR | G13: SUNET
B14: INSTANCE-p1.2xlarge.16d | D14: =INSTANCE_p1.4xlarge.16d_SEK/2 -> 6840 | E14: =D14*SEK -> 6840 | F14: =D14*EUR -> 642.96
B15: INSTANCE-p1.4xlarge.16d | D15: 13680 | E15: =D15*SEK -> 13680 | F15: =D15*EUR -> 1285.92
B16: INSTANCE-p1.8xlarge.32d | D16: =INSTANCE_p1.4xlarge.16d_SEK*2 -> 27360 | E16: =D16*SEK -> 27360 | F16: =D16*EUR -> 2571.84
B18: Safespring Compute | D18: Prissättning | E18: SEK | F18: EUR | G18: SUNET
B19: VOLUME-large | D19: 1.2 | E19: =D19*SEK -> 1.2 | F19: =D19*EUR -> 0.1128 | G19: =(D19*(1+Safespring.price.increase))*(1+sunet.price.increase) -> 1.2
B20: VOLUME-fast | D20: 3.6 | E20: =D20*SEK -> 3.6 | F20: =D20*EUR -> 0.3384 | G20: =(D20*(1+Safespring.price.increase))*(1+sunet.price.increase) -> 3.6
B22: Safespring Backup | D22: Prissättning | E22: SEK | F22: EUR | G22: SUNET
B23: BAAS-on.demand | D23: 2.45 | E23: =D23*SEK -> 2.45 | F23: =D23*EUR -> 0.2303
B24: BAAS-small.fee | D24: 5500 | E24: =D24*SEK -> 5500 | F24: =D24*EUR -> 517
B25: BAAS-large.fee | D25: 9500 | E25: =D25*SEK -> 9500 | F25: =D25*EUR -> 893
B26: BAAS-small | D26: 1.75 | E26: =D26*SEK -> 1.75 | F26: =D26*EUR -> 0.1645
B27: BAAS-large | D27: 0.92 | E27: =D27*SEK -> 0.92 | F27: =D27*EUR -> 0.08648
B29: Safespring Storage | D29: Prissättning | E29: SEK | F29: EUR | G29: SUNET
B30: S3-storage.50 | D30: 500 | E30: =D30*SEK -> 500 | F30: =D30*EUR -> 47 | G30: 0.35
B31: S3-storage.100 | D31: 500 | E31: =D31*SEK -> 500 | F31: =D31*EUR -> 47 | G31: 0.19
B32: S3-storage.500 | D32: 500 | E32: =D32*SEK -> 500 | F32: =D32*EUR -> 47 | G32: 0.1
B33: S3-storage.1000 | D33: 500 | E33: =D33*SEK -> 500 | F33: =D33*EUR -> 47 | G33: 0.06
B34: S3-storage.quote | D34: Be om offert | E34: =D34 -> Be om offert | F34: Request a quote | G34: =S3_storage.quote_SEK -> Be om offert
B35: S3-archive.50 | D35: 350 | E35: =D35*SEK -> 350 | F35: =D35*EUR -> 32.9 | G35: 0.35
B36: S3-archive.100 | D36: 270 | E36: =D36*SEK -> 270 | F36: =D36*EUR -> 25.38 | G36: 0.19
B37: S3-archive.500 | D37: 200 | E37: =D37*SEK -> 200 | F37: =D37*EUR -> 18.8 | G37: 0.1
B38: S3-archive.1000 | D38: 185 | E38: =D38*SEK -> 185 | F38: =D38*EUR -> 17.39 | G38: 0.06
B39: S3-archive.quote | D39: Be om offert | E39: =D39 -> Be om offert | F39: Request a quote | G39: =S3_storage.quote_SEK -> Be om offert
B41: Nätverk | D41: Prissättning | E41: SEK | F41: EUR | G41: SUNET
B42: NET-publicv4 | D42: 25 | E42: =D42*SEK -> 25 | F42: =D42*EUR -> 2.35 | G42: N/A
B43: NET-publicv6 | D43: 0 | E43: =D43*SEK -> 0 | F43: =D43*EUR -> 0 | G43: N/A
B44: NET-ingress | D44: 0 | E44: =D44*SEK -> 0 | F44: =D44*EUR -> 0 | G44: N/A
B45: NET-egress | D45: 0 | E45: =D45*SEK -> 0 | F45: =D45*EUR -> 0 | G45: N/A
B46: NET-mgn.slb | D46: 275 | E46: =D46 -> 275 | F46: =D46*EUR -> 25.85 | G46: N/A
B47: NET-rdns | D47: 0 | E47: =D47*SEK -> 0 | F47: =D47*EUR -> 0 | G47: N/A
B48: NET-saferoute | D48: Begär offert | E48: =D48 -> Begär offert | F48: Request a quote | G48: =S3_storage.quote_SEK -> Be om offert
B49: NET-byoip | D49: 0 | E49: =D49*SEK -> 0 | F49: =D49*EUR -> 0 | G49: N/A
B51: Mjukvara | D51: Prissättning | E51: SEK | F51: EUR | G51: SUNET
B52: SW-win.ser.2016 & 2019 | D52: 175 | E52: =D52*SEK -> 175 | F52: =D52*EUR -> 16.45 | G52: N/A
B53: SW-ms.sql.ser | D53: 1229 | E53: =D53*SEK -> 1229 | F53: =D53*EUR -> 115.526 | G53: N/A
B54: SW-ms.sql.ser.ent | D54: 4766 | E54: =D54*SEK -> 4766 | F54: =D54*EUR -> 448.004 | G54: N/A
B55: SW-stackn | E55: Begär offert | F55: Request a quote | G55: N/A
B56: SW-nextcloud | E56: Begär offert | F56: Request a quote | G56: N/A
B57: SW-suse | E57: Begär offert | F57: Request a quote | G57: N/A
B58: SW-cluster.control | E58: 3x instanspris | F58: 3x instance price | G58: N/A
B59: SW-backup.ninja | D59: 400 | E59: =D59*SEK -> 400 | F59: =D59*EUR -> 37.6 | G59: N/A
B61: Plattformstjänster | D61: Prissättning | E61: SEK | F61: EUR | G61: SUNET
B62: PAAS-man.kubernetes24 | D62: Begär offert | E62: Begär offert | F62: Request a quote | G62: N/A
B63: PAAS-man.kubernetes8 | D63: Begär offert | E63: Begär offert | F63: Request a quote | G63: N/A
B64: PAAS-man.elasticsearch | D64: 2 | E64: =D64 -> 2 | F64: =D64*EUR -> 0.188 | G64: N/A
B65: PAAS-man.redis | D65: 2 | E65: =D65 -> 2 | F65: =D65*EUR -> 0.188 | G65: N/A
B66: PAAS-man.nats | D66: 2 | E66: =D66 -> 2 | F66: =D66*EUR -> 0.188 | G66: N/A
B67: PAAS-man.mariadb | D67: 2 | E67: =D67 -> 2 | F67: =D67*EUR -> 0.188 | G67: N/A
B68: PAAS-openshift | D68: 0 | E68: Begär offert | F68: Request a quote | G68: N/A
B70: Konsulttjänster | D70: Prissättning | E70: SEK | F70: EUR | G70: SUNET
B71: PS-consult.jun | D71: 1127 | E71: =D71*SEK -> 1127 | F71: =D71*EUR -> 105.938 | G71: N/A
B72: PS-consult.sen | D72: 1374 | E72: =D72*SEK -> 1374 | F72: =D72*EUR -> 129.156 | G72: N/A
B73: PS-cloudarch.jun | D73: 1277 | E73: =D73*SEK -> 1277 | F73: =D73*EUR -> 120.038 | G73: N/A
B74: PS-cloudarch.sen | D74: 1374 | E74: =D74*SEK -> 1374 | F74: =D74*EUR -> 129.156 | G74: N/A
B75: PS-pm.jun | D75: 1139 | E75: =D75*SEK -> 1139 | F75: =D75*EUR -> 107.066 | G75: N/A
B76: PS-pm.sen | D76: 1374 | E76: =D76*SEK -> 1374 | F76: =D76*EUR -> 129.156 | G76: N/A
